{
    "language": "cmake",
    "words": [
        {
            "word": "set",
            "count": "477,438"
        },
        {
            "word": "endif",
            "count": "423,336"
        },
        {
            "word": "the",
            "count": "386,153"
        },
        {
            "word": "if",
            "count": "332,769"
        },
        {
            "word": "to",
            "count": "232,006"
        },
        {
            "word": "SET",
            "count": "216,868"
        },
        {
            "word": "NOT",
            "count": "203,806"
        },
        {
            "word": "cmake",
            "count": "156,350"
        },
        {
            "word": "include",
            "count": "151,160"
        },
        {
            "word": "ENDIF",
            "count": "144,379"
        },
        {
            "word": "for",
            "count": "141,871"
        },
        {
            "word": "of",
            "count": "138,035"
        },
        {
            "word": "IF",
            "count": "117,734"
        },
        {
            "word": "file",
            "count": "116,270"
        },
        {
            "word": "else",
            "count": "114,788"
        },
        {
            "word": "CMAKE_INSTALL_COMPONENT",
            "count": "109,345"
        },
        {
            "word": "is",
            "count": "109,112"
        },
        {
            "word": "and",
            "count": "99,033"
        },
        {
            "word": "usr",
            "count": "95,850"
        },
        {
            "word": "list",
            "count": "88,020"
        },
        {
            "word": "a",
            "count": "82,534"
        },
        {
            "word": "in",
            "count": "81,823"
        },
        {
            "word": "STREQUAL",
            "count": "81,586"
        },
        {
            "word": "The",
            "count": "76,248"
        },
        {
            "word": "this",
            "count": "75,473"
        },
        {
            "word": "lib",
            "count": "74,008"
        },
        {
            "word": "h",
            "count": "66,590"
        },
        {
            "word": "message",
            "count": "65,679"
        },
        {
            "word": "cmakedefine",
            "count": "61,209"
        },
        {
            "word": "be",
            "count": "60,500"
        },
        {
            "word": "OR",
            "count": "56,360"
        },
        {
            "word": "APPEND",
            "count": "56,236"
        },
        {
            "word": "endforeach",
            "count": "55,985"
        },
        {
            "word": "are",
            "count": "50,796"
        },
        {
            "word": "name",
            "count": "48,822"
        },
        {
            "word": "target",
            "count": "48,194"
        },
        {
            "word": "library",
            "count": "47,096"
        },
        {
            "word": "STATUS",
            "count": "46,859"
        },
        {
            "word": "DEFINED",
            "count": "46,699"
        },
        {
            "word": "not",
            "count": "45,801"
        },
        {
            "word": "CACHE",
            "count": "45,626"
        },
        {
            "word": "will",
            "count": "45,057"
        },
        {
            "word": "COMPONENT",
            "count": "45,022"
        },
        {
            "word": "files",
            "count": "44,355"
        },
        {
            "word": "CMAKE_INSTALL_CONFIG_NAME",
            "count": "44,008"
        },
        {
            "word": "share",
            "count": "43,778"
        },
        {
            "word": "CMAKE_INSTALL_PREFIX",
            "count": "43,268"
        },
        {
            "word": "string",
            "count": "42,891"
        },
        {
            "word": "local",
            "count": "41,907"
        },
        {
            "word": "with",
            "count": "39,699"
        },
        {
            "word": "REPLACE",
            "count": "39,646"
        },
        {
            "word": "from",
            "count": "39,319"
        },
        {
            "word": "that",
            "count": "38,795"
        },
        {
            "word": "This",
            "count": "37,797"
        },
        {
            "word": "MATCHES",
            "count": "37,779"
        },
        {
            "word": "opt",
            "count": "37,368"
        },
        {
            "word": "or",
            "count": "37,342"
        },
        {
            "word": "Set",
            "count": "36,962"
        },
        {
            "word": "CMakeFiles",
            "count": "36,065"
        },
        {
            "word": "ELSE",
            "count": "35,920"
        },
        {
            "word": "foreach",
            "count": "35,606"
        },
        {
            "word": "STRING",
            "count": "35,296"
        },
        {
            "word": "version",
            "count": "35,005"
        },
        {
            "word": "dir",
            "count": "34,798"
        },
        {
            "word": "REGEX",
            "count": "33,938"
        },
        {
            "word": "which",
            "count": "33,851"
        },
        {
            "word": "by",
            "count": "33,625"
        },
        {
            "word": "install",
            "count": "33,494"
        },
        {
            "word": "AND",
            "count": "33,464"
        },
        {
            "word": "elseif",
            "count": "33,221"
        },
        {
            "word": "it",
            "count": "32,782"
        },
        {
            "word": "on",
            "count": "31,972"
        },
        {
            "word": "path",
            "count": "31,585"
        },
        {
            "word": "as",
            "count": "31,404"
        },
        {
            "word": "dependencies",
            "count": "31,326"
        },
        {
            "word": "TRUE",
            "count": "31,307"
        },
        {
            "word": "lang",
            "count": "31,256"
        },
        {
            "word": "build",
            "count": "30,616"
        },
        {
            "word": "WIN32",
            "count": "30,606"
        },
        {
            "word": "CMake",
            "count": "30,433"
        },
        {
            "word": "If",
            "count": "29,988"
        },
        {
            "word": "module",
            "count": "29,945"
        },
        {
            "word": "C",
            "count": "29,593"
        },
        {
            "word": "libraries",
            "count": "29,501"
        },
        {
            "word": "home",
            "count": "29,046"
        },
        {
            "word": "use",
            "count": "28,641"
        },
        {
            "word": "PATHS",
            "count": "28,488"
        },
        {
            "word": "configuration",
            "count": "28,445"
        },
        {
            "word": "BUILD_TYPE",
            "count": "28,100"
        },
        {
            "word": "used",
            "count": "27,567"
        },
        {
            "word": "CMAKE_C_TARGET_INCLUDE_PATH",
            "count": "27,140"
        },
        {
            "word": "Modules",
            "count": "26,929"
        },
        {
            "word": "Unspecified",
            "count": "26,875"
        },
        {
            "word": "endmacro",
            "count": "26,654"
        },
        {
            "word": "endfunction",
            "count": "26,637"
        },
        {
            "word": "ENV",
            "count": "26,577"
        },
        {
            "word": "variables",
            "count": "26,504"
        },
        {
            "word": "language",
            "count": "25,919"
        },
        {
            "word": "tag",
            "count": "25,818"
        },
        {
            "word": "found",
            "count": "25,309"
        },
        {
            "word": "you",
            "count": "25,227"
        },
        {
            "word": "YES",
            "count": "25,047"
        },
        {
            "word": "CXX",
            "count": "24,559"
        },
        {
            "word": "all",
            "count": "24,356"
        },
        {
            "word": "directory",
            "count": "24,176"
        },
        {
            "word": "src",
            "count": "24,060"
        },
        {
            "word": "n",
            "count": "23,806"
        },
        {
            "word": "MESSAGE",
            "count": "23,576"
        },
        {
            "word": "COMMAND",
            "count": "23,361"
        },
        {
            "word": "default",
            "count": "23,151"
        },
        {
            "word": "can",
            "count": "23,073"
        },
        {
            "word": "ARGN",
            "count": "22,788"
        },
        {
            "word": "have",
            "count": "22,729"
        },
        {
            "word": "function",
            "count": "22,379"
        },
        {
            "word": "macro",
            "count": "22,172"
        },
        {
            "word": "return",
            "count": "22,135"
        },
        {
            "word": "INTERNAL",
            "count": "21,968"
        },
        {
            "word": "implicit",
            "count": "21,897"
        },
        {
            "word": "we",
            "count": "21,869"
        },
        {
            "word": "component",
            "count": "21,696"
        },
        {
            "word": "NAMES",
            "count": "21,385"
        },
        {
            "word": "prefix",
            "count": "21,196"
        },
        {
            "word": "DependInfo",
            "count": "20,829"
        },
        {
            "word": "ON",
            "count": "20,708"
        },
        {
            "word": "ENDFOREACH",
            "count": "20,568"
        },
        {
            "word": "generated",
            "count": "20,269"
        },
        {
            "word": "define",
            "count": "20,237"
        },
        {
            "word": "paths",
            "count": "20,121"
        },
        {
            "word": "search",
            "count": "20,084"
        },
        {
            "word": "FILE",
            "count": "20,082"
        },
        {
            "word": "FATAL_ERROR",
            "count": "19,670"
        },
        {
            "word": "each",
            "count": "19,563"
        },
        {
            "word": "t",
            "count": "19,487"
        },
        {
            "word": "NO",
            "count": "18,948"
        },
        {
            "word": "bin",
            "count": "18,907"
        },
        {
            "word": "find_package",
            "count": "18,814"
        },
        {
            "word": "TARGET",
            "count": "18,632"
        },
        {
            "word": "variable",
            "count": "18,373"
        },
        {
            "word": "output",
            "count": "18,265"
        },
        {
            "word": "compiler",
            "count": "18,149"
        },
        {
            "word": "source",
            "count": "18,119"
        },
        {
            "word": "Install",
            "count": "18,113"
        },
        {
            "word": "OFF",
            "count": "17,996"
        },
        {
            "word": "find",
            "count": "17,612"
        },
        {
            "word": "flags",
            "count": "17,042"
        },
        {
            "word": "header",
            "count": "16,985"
        },
        {
            "word": "dependency",
            "count": "16,915"
        },
        {
            "word": "einstein",
            "count": "16,851"
        },
        {
            "word": "openairinterface5g",
            "count": "16,851"
        },
        {
            "word": "c",
            "count": "16,722"
        },
        {
            "word": "FOREACH",
            "count": "16,696"
        },
        {
            "word": "PATH",
            "count": "16,661"
        },
        {
            "word": "int",
            "count": "16,573"
        },
        {
            "word": "unset",
            "count": "16,017"
        },
        {
            "word": "so",
            "count": "15,838"
        },
        {
            "word": "only",
            "count": "15,786"
        },
        {
            "word": "value",
            "count": "15,743"
        },
        {
            "word": "APPLE",
            "count": "15,591"
        },
        {
            "word": "needed",
            "count": "15,531"
        },
        {
            "word": "EQUAL",
            "count": "15,520"
        },
        {
            "word": "ros",
            "count": "15,489"
        },
        {
            "word": "option",
            "count": "15,466"
        },
        {
            "word": "test",
            "count": "15,332"
        },
        {
            "word": "PROPERTY",
            "count": "15,237"
        },
        {
            "word": "core",
            "count": "15,122"
        },
        {
            "word": "Define",
            "count": "14,927"
        },
        {
            "word": "EXISTS",
            "count": "14,827"
        },
        {
            "word": "FindPackageHandleStandardArgs",
            "count": "14,660"
        },
        {
            "word": "CMAKE_INSTALL_SO_NO_EXE",
            "count": "14,355"
        },
        {
            "word": "CHECK_FUNCTION_EXISTS",
            "count": "14,171"
        },
        {
            "word": "_",
            "count": "14,170"
        },
        {
            "word": "txt",
            "count": "13,961"
        },
        {
            "word": "PATH_SUFFIXES",
            "count": "13,928"
        },
        {
            "word": "following",
            "count": "13,907"
        },
        {
            "word": "an",
            "count": "13,805"
        },
        {
            "word": "command",
            "count": "13,748"
        },
        {
            "word": "FALSE",
            "count": "13,624"
        },
        {
            "word": "s",
            "count": "13,496"
        },
        {
            "word": "catkin",
            "count": "13,263"
        },
        {
            "word": "REMOVE_RECURSE",
            "count": "13,242"
        },
        {
            "word": "system",
            "count": "13,223"
        },
        {
            "word": "PARENT_SCOPE",
            "count": "13,206"
        },
        {
            "word": "MSVC",
            "count": "13,186"
        },
        {
            "word": "should",
            "count": "13,119"
        },
        {
            "word": "clean",
            "count": "13,085"
        },
        {
            "word": "rules",
            "count": "12,838"
        },
        {
            "word": "CMAKE_BINARY_DIR",
            "count": "12,735"
        },
        {
            "word": "debug",
            "count": "12,732"
        },
        {
            "word": "INCLUDE",
            "count": "12,682"
        },
        {
            "word": "PROPERTIES",
            "count": "12,643"
        },
        {
            "word": "UNIX",
            "count": "12,631"
        },
        {
            "word": "A",
            "count": "12,372"
        },
        {
            "word": "DESTINATION",
            "count": "12,370"
        },
        {
            "word": "Ee",
            "count": "12,314"
        },
        {
            "word": "directories",
            "count": "12,243"
        },
        {
            "word": "get_filename_component",
            "count": "12,219"
        },
        {
            "word": "scanning",
            "count": "12,158"
        },
        {
            "word": "Per",
            "count": "12,079"
        },
        {
            "word": "HINTS",
            "count": "11,947"
        },
        {
            "word": "sys",
            "count": "11,900"
        },
        {
            "word": "then",
            "count": "11,877"
        },
        {
            "word": "arg",
            "count": "11,843"
        },
        {
            "word": "links",
            "count": "11,689"
        },
        {
            "word": "installed",
            "count": "11,644"
        },
        {
            "word": "project",
            "count": "11,634"
        },
        {
            "word": "link",
            "count": "11,548"
        },
        {
            "word": "required",
            "count": "11,539"
        },
        {
            "word": "documentation",
            "count": "11,435"
        },
        {
            "word": "but",
            "count": "11,263"
        },
        {
            "word": "when",
            "count": "11,253"
        },
        {
            "word": "languages",
            "count": "11,073"
        },
        {
            "word": "using",
            "count": "11,000"
        },
        {
            "word": "CMAKE_CXX_FLAGS",
            "count": "10,977"
        },
        {
            "word": "cpp",
            "count": "10,918"
        },
        {
            "word": "need",
            "count": "10,918"
        },
        {
            "word": "Targets",
            "count": "10,910"
        },
        {
            "word": "main",
            "count": "10,775"
        },
        {
            "word": "For",
            "count": "10,716"
        },
        {
            "word": "CMAKE_DEPENDS_LANGUAGES",
            "count": "10,685"
        },
        {
            "word": "CMAKE_TARGET_LINKED_INFO_FILES",
            "count": "10,677"
        },
        {
            "word": "execute_process",
            "count": "10,587"
        },
        {
            "word": "DEPENDS",
            "count": "10,561"
        },
        {
            "word": "where",
            "count": "10,559"
        },
        {
            "word": "FORCE",
            "count": "10,535"
        },
        {
            "word": "defined",
            "count": "10,490"
        },
        {
            "word": "config",
            "count": "10,422"
        },
        {
            "word": "BOOL",
            "count": "10,380"
        },
        {
            "word": "VERSION",
            "count": "10,262"
        },
        {
            "word": "CMAKE_CURRENT_BINARY_DIR",
            "count": "10,230"
        },
        {
            "word": "CMAKE_COMMAND",
            "count": "10,083"
        },
        {
            "word": "Release",
            "count": "9,931"
        },
        {
            "word": "was",
            "count": "9,859"
        },
        {
            "word": "code",
            "count": "9,839"
        },
        {
            "word": "one",
            "count": "9,719"
        },
        {
            "word": "PREFIX",
            "count": "9,609"
        },
        {
            "word": "options",
            "count": "9,588"
        },
        {
            "word": "doxygen",
            "count": "9,582"
        },
        {
            "word": "package",
            "count": "9,571"
        },
        {
            "word": "g",
            "count": "9,480"
        },
        {
            "word": "has",
            "count": "9,363"
        },
        {
            "word": "indigo",
            "count": "9,301"
        },
        {
            "word": "definitions",
            "count": "9,260"
        },
        {
            "word": "Linux",
            "count": "9,177"
        },
        {
            "word": "other",
            "count": "9,158"
        },
        {
            "word": "support",
            "count": "9,076"
        },
        {
            "word": "_target",
            "count": "9,022"
        },
        {
            "word": "set_target_properties",
            "count": "8,997"
        },
        {
            "word": "VAR",
            "count": "8,954"
        },
        {
            "word": "make",
            "count": "8,920"
        },
        {
            "word": "OUTPUT_VARIABLE",
            "count": "8,915"
        },
        {
            "word": "no",
            "count": "8,885"
        },
        {
            "word": "Library",
            "count": "8,869"
        },
        {
            "word": "static",
            "count": "8,750"
        },
        {
            "word": "generate",
            "count": "8,726"
        },
        {
            "word": "your",
            "count": "8,673"
        },
        {
            "word": "find_library",
            "count": "8,660"
        },
        {
            "word": "CMAKE_SYSTEM_NAME",
            "count": "8,645"
        },
        {
            "word": "_index",
            "count": "8,639"
        },
        {
            "word": "see",
            "count": "8,632"
        },
        {
            "word": "9_",
            "count": "8,604"
        },
        {
            "word": "Za",
            "count": "8,536"
        },
        {
            "word": "mark_as_advanced",
            "count": "8,484"
        },
        {
            "word": "set_property",
            "count": "8,404"
        },
        {
            "word": "specify",
            "count": "8,404"
        },
        {
            "word": "WORKING_DIRECTORY",
            "count": "8,345"
        },
        {
            "word": "libs",
            "count": "8,327"
        },
        {
            "word": "Debug",
            "count": "8,300"
        },
        {
            "word": "do",
            "count": "8,289"
        },
        {
            "word": "CHECK_INCLUDE_FILES",
            "count": "8,264"
        },
        {
            "word": "targets",
            "count": "8,248"
        },
        {
            "word": "z0",
            "count": "8,246"
        },
        {
            "word": "add",
            "count": "8,237"
        },
        {
            "word": "flag",
            "count": "8,236"
        },
        {
            "word": "getting",
            "count": "8,236"
        },
        {
            "word": "_language",
            "count": "8,217"
        },
        {
            "word": "e",
            "count": "8,100"
        },
        {
            "word": "REQUIRED",
            "count": "8,038"
        },
        {
            "word": "CMAKE_DEPENDS_CHECK_CXX",
            "count": "7,990"
        },
        {
            "word": "done",
            "count": "7,974"
        },
        {
            "word": "type",
            "count": "7,974"
        },
        {
            "word": "var",
            "count": "7,953"
        },
        {
            "word": "modules",
            "count": "7,940"
        },
        {
            "word": "run",
            "count": "7,923"
        },
        {
            "word": "lib64",
            "count": "7,922"
        },
        {
            "word": "ENDMACRO",
            "count": "7,871"
        },
        {
            "word": "result",
            "count": "7,836"
        },
        {
            "word": "full",
            "count": "7,820"
        },
        {
            "word": "CMAKE_CURRENT_SOURCE_DIR",
            "count": "7,813"
        },
        {
            "word": "at",
            "count": "7,796"
        },
        {
            "word": "NO_DEFAULT_PATH",
            "count": "7,783"
        },
        {
            "word": "true",
            "count": "7,758"
        },
        {
            "word": "platform",
            "count": "7,722"
        },
        {
            "word": "Unix",
            "count": "7,720"
        },
        {
            "word": "E",
            "count": "7,677"
        },
        {
            "word": "toolchain",
            "count": "7,674"
        },
        {
            "word": "CMAKE_BUILD_TYPE",
            "count": "7,670"
        },
        {
            "word": "also",
            "count": "7,647"
        },
        {
            "word": "ONLY",
            "count": "7,595"
        },
        {
            "word": "NDK",
            "count": "7,574"
        },
        {
            "word": "script",
            "count": "7,573"
        },
        {
            "word": "http",
            "count": "7,570"
        },
        {
            "word": "_name",
            "count": "7,446"
        },
        {
            "word": "CMAKE_CXX_TARGET_INCLUDE_PATH",
            "count": "7,406"
        },
        {
            "word": "OUTPUT",
            "count": "7,390"
        },
        {
            "word": "these",
            "count": "7,388"
        },
        {
            "word": "available",
            "count": "7,382"
        },
        {
            "word": "user",
            "count": "7,367"
        },
        {
            "word": "must",
            "count": "7,350"
        },
        {
            "word": "Boost",
            "count": "7,346"
        },
        {
            "word": "names",
            "count": "7,252"
        },
        {
            "word": "cache",
            "count": "7,210"
        },
        {
            "word": "qt4",
            "count": "7,201"
        },
        {
            "word": "ABSOLUTE",
            "count": "7,187"
        },
        {
            "word": "sw",
            "count": "7,138"
        },
        {
            "word": "I",
            "count": "7,131"
        },
        {
            "word": "information",
            "count": "7,097"
        },
        {
            "word": "arguments",
            "count": "7,087"
        },
        {
            "word": "vtk",
            "count": "7,084"
        },
        {
            "word": "CMAKE_SOURCE_DIR",
            "count": "7,049"
        },
        {
            "word": "Windows",
            "count": "7,040"
        },
        {
            "word": "tests",
            "count": "7,003"
        },
        {
            "word": "shared",
            "count": "6,971"
        },
        {
            "word": "up",
            "count": "6,970"
        },
        {
            "word": "more",
            "count": "6,951"
        },
        {
            "word": "Frameworks",
            "count": "6,948"
        },
        {
            "word": "Preprocessor",
            "count": "6,942"
        },
        {
            "word": "proj",
            "count": "6,876"
        },
        {
            "word": "defines",
            "count": "6,811"
        },
        {
            "word": "line",
            "count": "6,799"
        },
        {
            "word": "To",
            "count": "6,795"
        },
        {
            "word": "Check",
            "count": "6,780"
        },
        {
            "word": "openair2",
            "count": "6,722"
        },
        {
            "word": "CMAKE_ASM_TARGET_INCLUDE_PATH",
            "count": "6,702"
        },
        {
            "word": "CMAKE_Fortran_TARGET_INCLUDE_PATH",
            "count": "6,702"
        },
        {
            "word": "GREATER",
            "count": "6,676"
        },
        {
            "word": "release",
            "count": "6,660"
        },
        {
            "word": "CMAKE_",
            "count": "6,659"
        },
        {
            "word": "x86",
            "count": "6,649"
        },
        {
            "word": "commands",
            "count": "6,633"
        },
        {
            "word": "FIND_LIBRARY",
            "count": "6,580"
        },
        {
            "word": "executable",
            "count": "6,578"
        },
        {
            "word": "specified",
            "count": "6,527"
        },
        {
            "word": "headers",
            "count": "6,523"
        },
        {
            "word": "CMAKE",
            "count": "6,519"
        },
        {
            "word": "case",
            "count": "6,476"
        },
        {
            "word": "specific",
            "count": "6,476"
        },
        {
            "word": "add_custom_command",
            "count": "6,461"
        },
        {
            "word": "cn",
            "count": "6,393"
        },
        {
            "word": "openair",
            "count": "6,379"
        },
        {
            "word": "some",
            "count": "6,367"
        },
        {
            "word": "d",
            "count": "6,346"
        },
        {
            "word": "time",
            "count": "6,336"
        },
        {
            "word": "CMAKE_C_FLAGS",
            "count": "6,330"
        },
        {
            "word": "includes",
            "count": "6,303"
        },
        {
            "word": "Use",
            "count": "6,301"
        },
        {
            "word": "Find",
            "count": "6,273"
        },
        {
            "word": "i",
            "count": "6,269"
        },
        {
            "word": "CMAKE_TARGET_DEFINITIONS",
            "count": "6,265"
        },
        {
            "word": "Makefiles",
            "count": "6,262"
        },
        {
            "word": "android",
            "count": "6,221"
        },
        {
            "word": "does",
            "count": "6,219"
        },
        {
            "word": "D",
            "count": "6,200"
        },
        {
            "word": "basename",
            "count": "6,178"
        },
        {
            "word": "check",
            "count": "6,148"
        },
        {
            "word": "demos",
            "count": "6,137"
        },
        {
            "word": "same",
            "count": "6,118"
        },
        {
            "word": "try",
            "count": "6,074"
        },
        {
            "word": "environment",
            "count": "6,066"
        },
        {
            "word": "sources",
            "count": "6,058"
        },
        {
            "word": "Once",
            "count": "5,939"
        },
        {
            "word": "any",
            "count": "5,936"
        },
        {
            "word": "ANDROID_CXX_FLAGS",
            "count": "5,935"
        },
        {
            "word": "add_definitions",
            "count": "5,912"
        },
        {
            "word": "compile",
            "count": "5,905"
        },
        {
            "word": "requires",
            "count": "5,895"
        },
        {
            "word": "math",
            "count": "5,830"
        },
        {
            "word": "OUTPUT_STRIP_TRAILING_WHITESPACE",
            "count": "5,827"
        },
        {
            "word": "Build",
            "count": "5,789"
        },
        {
            "word": "GET",
            "count": "5,779"
        },
        {
            "word": "get",
            "count": "5,770"
        },
        {
            "word": "framework",
            "count": "5,736"
        },
        {
            "word": "Version",
            "count": "5,732"
        },
        {
            "word": "Add",
            "count": "5,728"
        },
        {
            "word": "here",
            "count": "5,727"
        },
        {
            "word": "testing",
            "count": "5,699"
        },
        {
            "word": "out",
            "count": "5,680"
        },
        {
            "word": "CMakeLists",
            "count": "5,646"
        },
        {
            "word": "them",
            "count": "5,607"
        },
        {
            "word": "INSTALL",
            "count": "5,583"
        },
        {
            "word": "OS",
            "count": "5,583"
        },
        {
            "word": "part",
            "count": "5,560"
        },
        {
            "word": "binary",
            "count": "5,506"
        },
        {
            "word": "~",
            "count": "5,504"
        },
        {
            "word": "Ii",
            "count": "5,490"
        },
        {
            "word": "DOC",
            "count": "5,462"
        },
        {
            "word": "We",
            "count": "5,461"
        },
        {
            "word": "without",
            "count": "5,443"
        },
        {
            "word": "details",
            "count": "5,437"
        },
        {
            "word": "values",
            "count": "5,420"
        },
        {
            "word": "included",
            "count": "5,394"
        },
        {
            "word": "Note",
            "count": "5,385"
        },
        {
            "word": "distribute",
            "count": "5,340"
        },
        {
            "word": "top",
            "count": "5,310"
        },
        {
            "word": "false",
            "count": "5,294"
        },
        {
            "word": "they",
            "count": "5,289"
        },
        {
            "word": "number",
            "count": "5,283"
        },
        {
            "word": "Doxygen",
            "count": "5,253"
        },
        {
            "word": "given",
            "count": "5,238"
        },
        {
            "word": "listed",
            "count": "5,236"
        },
        {
            "word": "before",
            "count": "5,217"
        },
        {
            "word": "Platform",
            "count": "5,215"
        },
        {
            "word": "CMAKE_REQUIRED_LIBRARIES",
            "count": "5,194"
        },
        {
            "word": "RESULT_VARIABLE",
            "count": "5,181"
        },
        {
            "word": "outside",
            "count": "5,179"
        },
        {
            "word": "ANDROID_NDK",
            "count": "5,170"
        },
        {
            "word": "find_path",
            "count": "5,147"
        },
        {
            "word": "already",
            "count": "5,128"
        },
        {
            "word": "FIND_PATH",
            "count": "5,122"
        },
        {
            "word": "first",
            "count": "5,120"
        },
        {
            "word": "into",
            "count": "5,101"
        },
        {
            "word": "void",
            "count": "5,090"
        },
        {
            "word": "Clang",
            "count": "5,079"
        },
        {
            "word": "NAME",
            "count": "5,063"
        },
        {
            "word": "mysql",
            "count": "5,055"
        },
        {
            "word": "_var",
            "count": "5,052"
        },
        {
            "word": "location",
            "count": "5,036"
        },
        {
            "word": "CMAKE_CURRENT_LIST_FILE",
            "count": "5,023"
        },
        {
            "word": "MINGW",
            "count": "5,022"
        },
        {
            "word": "there",
            "count": "5,018"
        },
        {
            "word": "Boost_",
            "count": "5,012"
        },
        {
            "word": "log",
            "count": "4,991"
        },
        {
            "word": "LENGTH",
            "count": "4,983"
        },
        {
            "word": "char",
            "count": "4,972"
        },
        {
            "word": "host",
            "count": "4,967"
        },
        {
            "word": "CMAKE_ABSOLUTE_DESTINATION_FILES",
            "count": "4,956"
        },
        {
            "word": "_FOUND",
            "count": "4,951"
        },
        {
            "word": "ELSEIF",
            "count": "4,930"
        },
        {
            "word": "MODULE",
            "count": "4,930"
        },
        {
            "word": "provided",
            "count": "4,916"
        },
        {
            "word": "like",
            "count": "4,913"
        },
        {
            "word": "X",
            "count": "4,900"
        },
        {
            "word": "FILES",
            "count": "4,898"
        },
        {
            "word": "LIB",
            "count": "4,823"
        },
        {
            "word": "get_property",
            "count": "4,822"
        },
        {
            "word": "o",
            "count": "4,817"
        },
        {
            "word": "Generated",
            "count": "4,795"
        },
        {
            "word": "error",
            "count": "4,795"
        },
        {
            "word": "external",
            "count": "4,791"
        },
        {
            "word": "instead",
            "count": "4,787"
        },
        {
            "word": "boost",
            "count": "4,783"
        },
        {
            "word": "remove",
            "count": "4,779"
        },
        {
            "word": "Android",
            "count": "4,774"
        },
        {
            "word": "create",
            "count": "4,756"
        },
        {
            "word": "CMAKE_INSTALL_DO_STRIP",
            "count": "4,743"
        },
        {
            "word": "SDL2",
            "count": "4,740"
        },
        {
            "word": "step",
            "count": "4,730"
        },
        {
            "word": "NOTFOUND",
            "count": "4,726"
        },
        {
            "word": "CMAKE_SIZEOF_VOID_P",
            "count": "4,719"
        },
        {
            "word": "class",
            "count": "4,709"
        },
        {
            "word": "org",
            "count": "4,683"
        },
        {
            "word": "enabled",
            "count": "4,675"
        },
        {
            "word": "substitute",
            "count": "4,668"
        },
        {
            "word": "Include",
            "count": "4,665"
        },
        {
            "word": "dll",
            "count": "4,665"
        },
        {
            "word": "extra",
            "count": "4,655"
        },
        {
            "word": "level",
            "count": "4,616"
        },
        {
            "word": "FIND",
            "count": "4,600"
        },
        {
            "word": "fno",
            "count": "4,595"
        },
        {
            "word": "work",
            "count": "4,577"
        },
        {
            "word": "custom",
            "count": "4,576"
        },
        {
            "word": "MACRO",
            "count": "4,575"
        },
        {
            "word": "include_directories",
            "count": "4,575"
        },
        {
            "word": "_LIBRARY",
            "count": "4,569"
        },
        {
            "word": "CMAKE_COMPILER_IS_GNUCXX",
            "count": "4,552"
        },
        {
            "word": "Qt",
            "count": "4,551"
        },
        {
            "word": "x86_64",
            "count": "4,528"
        },
        {
            "word": "EXPR",
            "count": "4,523"
        },
        {
            "word": "types",
            "count": "4,510"
        },
        {
            "word": "DO",
            "count": "4,506"
        },
        {
            "word": "MARK_AS_ADVANCED",
            "count": "4,500"
        },
        {
            "word": "CMAKE_C_INCLUDE_REGEX_COMPLAIN",
            "count": "4,488"
        },
        {
            "word": "CMAKE_C_INCLUDE_REGEX_SCAN",
            "count": "4,486"
        },
        {
            "word": "Ll",
            "count": "4,470"
        },
        {
            "word": "configure",
            "count": "4,456"
        },
        {
            "word": "arm",
            "count": "4,455"
        },
        {
            "word": "res",
            "count": "4,442"
        },
        {
            "word": "runtime",
            "count": "4,435"
        },
        {
            "word": "GET_FILENAME_COMPONENT",
            "count": "4,431"
        },
        {
            "word": "ANDROID_STANDALONE_TOOLCHAIN",
            "count": "4,421"
        },
        {
            "word": "com",
            "count": "4,419"
        },
        {
            "word": "Rr",
            "count": "4,414"
        },
        {
            "word": "python",
            "count": "4,414"
        },
        {
            "word": "long",
            "count": "4,407"
        },
        {
            "word": "after",
            "count": "4,405"
        },
        {
            "word": "because",
            "count": "4,404"
        },
        {
            "word": "extras",
            "count": "4,386"
        },
        {
            "word": "ARGS",
            "count": "4,362"
        },
        {
            "word": "installation",
            "count": "4,346"
        },
        {
            "word": "HTML",
            "count": "4,328"
        },
        {
            "word": "linux",
            "count": "4,320"
        },
        {
            "word": "optimized",
            "count": "4,312"
        },
        {
            "word": "CMAKE_SYSTEM_PROCESSOR",
            "count": "4,311"
        },
        {
            "word": "TOUPPER",
            "count": "4,308"
        },
        {
            "word": "input",
            "count": "4,307"
        },
        {
            "word": "x",
            "count": "4,291"
        },
        {
            "word": "depends",
            "count": "4,289"
        },
        {
            "word": "break",
            "count": "4,280"
        },
        {
            "word": "CMAKE_CURRENT_LIST_DIR",
            "count": "4,268"
        },
        {
            "word": "listname",
            "count": "4,261"
        },
        {
            "word": "root",
            "count": "4,244"
        },
        {
            "word": "UTIL",
            "count": "4,195"
        },
        {
            "word": "versions",
            "count": "4,195"
        },
        {
            "word": "__",
            "count": "4,178"
        },
        {
            "word": "m",
            "count": "4,178"
        },
        {
            "word": "hpp",
            "count": "4,164"
        },
        {
            "word": "distribution",
            "count": "4,159"
        },
        {
            "word": "just",
            "count": "4,142"
        },
        {
            "word": "common",
            "count": "4,138"
        },
        {
            "word": "LIST",
            "count": "4,135"
        },
        {
            "word": "generator",
            "count": "4,131"
        },
        {
            "word": "tree",
            "count": "4,128"
        },
        {
            "word": "exit",
            "count": "4,104"
        },
        {
            "word": "Generator",
            "count": "4,102"
        },
        {
            "word": "LESS",
            "count": "4,102"
        },
        {
            "word": "msg",
            "count": "4,097"
        },
        {
            "word": "components",
            "count": "4,081"
        },
        {
            "word": "configure_file",
            "count": "4,078"
        },
        {
            "word": "struct",
            "count": "4,069"
        },
        {
            "word": "don",
            "count": "4,068"
        },
        {
            "word": "FIND_SFML_COMPONENT_UPPER",
            "count": "4,060"
        },
        {
            "word": "argument",
            "count": "4,047"
        },
        {
            "word": "empty",
            "count": "4,031"
        },
        {
            "word": "CYGWIN",
            "count": "4,022"
        },
        {
            "word": "VERSION_LESS",
            "count": "4,010"
        },
        {
            "word": "Wl",
            "count": "4,000"
        },
        {
            "word": "building",
            "count": "3,998"
        },
        {
            "word": "copy",
            "count": "3,990"
        },
        {
            "word": "cxx",
            "count": "3,990"
        },
        {
            "word": "added",
            "count": "3,987"
        },
        {
            "word": "Makefile",
            "count": "3,962"
        },
        {
            "word": "SFML_",
            "count": "3,957"
        },
        {
            "word": "been",
            "count": "3,947"
        },
        {
            "word": "gtest",
            "count": "3,939"
        },
        {
            "word": "MPI",
            "count": "3,935"
        },
        {
            "word": "linker",
            "count": "3,919"
        },
        {
            "word": "WARNING",
            "count": "3,905"
        },
        {
            "word": "generated_file",
            "count": "3,880"
        },
        {
            "word": "based",
            "count": "3,874"
        },
        {
            "word": "non",
            "count": "3,856"
        },
        {
            "word": "Files",
            "count": "3,853"
        },
        {
            "word": "index",
            "count": "3,850"
        },
        {
            "word": "_LIBRARY_RELEASE",
            "count": "3,827"
        },
        {
            "word": "_flags",
            "count": "3,820"
        },
        {
            "word": "standard",
            "count": "3,819"
        },
        {
            "word": "want",
            "count": "3,811"
        },
        {
            "word": "SDL",
            "count": "3,810"
        },
        {
            "word": "against",
            "count": "3,804"
        },
        {
            "word": "new",
            "count": "3,797"
        },
        {
            "word": "Program",
            "count": "3,796"
        },
        {
            "word": "It",
            "count": "3,779"
        },
        {
            "word": "System",
            "count": "3,776"
        },
        {
            "word": "_NAME",
            "count": "3,764"
        },
        {
            "word": "See",
            "count": "3,759"
        },
        {
            "word": "EDIT",
            "count": "3,752"
        },
        {
            "word": "MySQL",
            "count": "3,746"
        },
        {
            "word": "find_program",
            "count": "3,743"
        },
        {
            "word": "example",
            "count": "3,741"
        },
        {
            "word": "unittests",
            "count": "3,740"
        },
        {
            "word": "git",
            "count": "3,737"
        },
        {
            "word": "_LIBRARY_DEBUG",
            "count": "3,702"
        },
        {
            "word": "etc",
            "count": "3,692"
        },
        {
            "word": "CMAKE_GENERATOR",
            "count": "3,684"
        },
        {
            "word": "its",
            "count": "3,667"
        },
        {
            "word": "setup",
            "count": "3,661"
        },
        {
            "word": "Python",
            "count": "3,653"
        },
        {
            "word": "ans",
            "count": "3,638"
        },
        {
            "word": "info",
            "count": "3,632"
        },
        {
            "word": "keep",
            "count": "3,625"
        },
        {
            "word": "SDK",
            "count": "3,597"
        },
        {
            "word": "v",
            "count": "3,580"
        },
        {
            "word": "CMAKE_CXX_COMPILER_ID",
            "count": "3,571"
        },
        {
            "word": "program",
            "count": "3,566"
        },
        {
            "word": "add_custom_target",
            "count": "3,550"
        },
        {
            "word": "IN",
            "count": "3,538"
        },
        {
            "word": "CMAKE_INSTALL_MANIFEST",
            "count": "3,498"
        },
        {
            "word": "QUIET",
            "count": "3,498"
        },
        {
            "word": "doc",
            "count": "3,486"
        },
        {
            "word": "optional",
            "count": "3,485"
        },
        {
            "word": "COPYING",
            "count": "3,481"
        },
        {
            "word": "sure",
            "count": "3,475"
        },
        {
            "word": "gcc",
            "count": "3,472"
        },
        {
            "word": "lists",
            "count": "3,468"
        },
        {
            "word": "Redistribution",
            "count": "3,466"
        },
        {
            "word": "target_link_libraries",
            "count": "3,459"
        },
        {
            "word": "cc",
            "count": "3,456"
        },
        {
            "word": "Darwin",
            "count": "3,452"
        },
        {
            "word": "foo",
            "count": "3,448"
        },
        {
            "word": "pthread",
            "count": "3,448"
        },
        {
            "word": "IS_ABSOLUTE",
            "count": "3,447"
        },
        {
            "word": "append",
            "count": "3,437"
        },
        {
            "word": "pkg",
            "count": "3,437"
        },
        {
            "word": "www",
            "count": "3,436"
        },
        {
            "word": "f",
            "count": "3,434"
        },
        {
            "word": "additional",
            "count": "3,420"
        },
        {
            "word": "well",
            "count": "3,418"
        },
        {
            "word": "CMAKE_C_INCLUDE_PATH",
            "count": "3,415"
        },
        {
            "word": "_LIBRARIES",
            "count": "3,413"
        },
        {
            "word": "html",
            "count": "3,409"
        },
        {
            "word": "CMakeDirectoryInformation",
            "count": "3,402"
        },
        {
            "word": "plugins",
            "count": "3,390"
        },
        {
            "word": "You",
            "count": "3,382"
        },
        {
            "word": "enable",
            "count": "3,368"
        },
        {
            "word": "CMAKE_CXX_COMPILER",
            "count": "3,353"
        },
        {
            "word": "Try",
            "count": "3,351"
        },
        {
            "word": "csw",
            "count": "3,337"
        },
        {
            "word": "No",
            "count": "3,336"
        },
        {
            "word": "would",
            "count": "3,330"
        },
        {
            "word": "data",
            "count": "3,319"
        },
        {
            "word": "Visual",
            "count": "3,256"
        },
        {
            "word": "PACKAGE_NAME",
            "count": "3,255"
        },
        {
            "word": "since",
            "count": "3,248"
        },
        {
            "word": "change",
            "count": "3,246"
        },
        {
            "word": "bit",
            "count": "3,245"
        },
        {
            "word": "exe",
            "count": "3,234"
        },
        {
            "word": "missing",
            "count": "3,233"
        },
        {
            "word": "Usage",
            "count": "3,232"
        },
        {
            "word": "always",
            "count": "3,232"
        },
        {
            "word": "subdirectories",
            "count": "3,232"
        },
        {
            "word": "__cmd",
            "count": "3,222"
        },
        {
            "word": "TARGET_NAME",
            "count": "3,219"
        },
        {
            "word": "relative",
            "count": "3,206"
        },
        {
            "word": "__libstl",
            "count": "3,196"
        },
        {
            "word": "CUDA",
            "count": "3,189"
        },
        {
            "word": "sets",
            "count": "3,188"
        },
        {
            "word": "armeabi",
            "count": "3,180"
        },
        {
            "word": "tools",
            "count": "3,176"
        },
        {
            "word": "regular",
            "count": "3,165"
        },
        {
            "word": "__var",
            "count": "3,161"
        },
        {
            "word": "macros",
            "count": "3,159"
        },
        {
            "word": "_prefix",
            "count": "3,158"
        },
        {
            "word": "py",
            "count": "3,154"
        },
        {
            "word": "Dd",
            "count": "3,145"
        },
        {
            "word": "_state",
            "count": "3,140"
        },
        {
            "word": "check_function_exists",
            "count": "3,139"
        },
        {
            "word": "NAS",
            "count": "3,138"
        },
        {
            "word": "exist",
            "count": "3,137"
        },
        {
            "word": "pkgConfig",
            "count": "3,134"
        },
        {
            "word": "ADD_CUSTOM_COMMAND",
            "count": "3,133"
        },
        {
            "word": "Bb",
            "count": "3,127"
        },
        {
            "word": "COMPILE_FLAGS",
            "count": "3,125"
        },
        {
            "word": "WRITE",
            "count": "3,125"
        },
        {
            "word": "about",
            "count": "3,124"
        },
        {
            "word": "unix",
            "count": "3,118"
        },
        {
            "word": "dirs",
            "count": "3,113"
        },
        {
            "word": "copied",
            "count": "3,108"
        },
        {
            "word": "filename",
            "count": "3,093"
        },
        {
            "word": "opm",
            "count": "3,093"
        },
        {
            "word": "doesn",
            "count": "3,092"
        },
        {
            "word": "outfile",
            "count": "3,078"
        },
        {
            "word": "CPack",
            "count": "3,074"
        },
        {
            "word": "Nn",
            "count": "3,068"
        },
        {
            "word": "whether",
            "count": "3,063"
        },
        {
            "word": "stdlib",
            "count": "3,058"
        },
        {
            "word": "materials",
            "count": "3,056"
        },
        {
            "word": "cmake_policy",
            "count": "3,048"
        },
        {
            "word": "handle",
            "count": "3,047"
        },
        {
            "word": "uses",
            "count": "3,046"
        },
        {
            "word": "standalone",
            "count": "3,034"
        },
        {
            "word": "Path",
            "count": "3,030"
        },
        {
            "word": "cmd",
            "count": "3,018"
        },
        {
            "word": "end",
            "count": "3,017"
        },
        {
            "word": "idir",
            "count": "3,015"
        },
        {
            "word": "tmp",
            "count": "3,002"
        },
        {
            "word": "groovy",
            "count": "2,995"
        },
        {
            "word": "Ss",
            "count": "2,985"
        },
        {
            "word": "put",
            "count": "2,984"
        },
        {
            "word": "setting",
            "count": "2,981"
        },
        {
            "word": "ANDROID_ABI",
            "count": "2,978"
        },
        {
            "word": "windows",
            "count": "2,977"
        },
        {
            "word": "ANDROID_LINKER_FLAGS",
            "count": "2,974"
        },
        {
            "word": "FILEPATH",
            "count": "2,971"
        },
        {
            "word": "contained",
            "count": "2,971"
        },
        {
            "word": "Intel",
            "count": "2,965"
        },
        {
            "word": "both",
            "count": "2,957"
        },
        {
            "word": "SCRIPTS",
            "count": "2,956"
        },
        {
            "word": "plugin",
            "count": "2,956"
        },
        {
            "word": "MPI_",
            "count": "2,947"
        },
        {
            "word": "warnings",
            "count": "2,947"
        },
        {
            "word": "look",
            "count": "2,945"
        },
        {
            "word": "nvcc",
            "count": "2,945"
        },
        {
            "word": "settings",
            "count": "2,944"
        },
        {
            "word": "contain",
            "count": "2,936"
        },
        {
            "word": "In",
            "count": "2,933"
        },
        {
            "word": "now",
            "count": "2,933"
        },
        {
            "word": "linking",
            "count": "2,931"
        },
        {
            "word": "related",
            "count": "2,929"
        },
        {
            "word": "eigen",
            "count": "2,923"
        },
        {
            "word": "CMAKE_ERROR_ON_ABSOLUTE_INSTALL_DESTINATION",
            "count": "2,921"
        },
        {
            "word": "CMAKE_WARN_ON_ABSOLUTE_INSTALL_DESTINATION",
            "count": "2,921"
        },
        {
            "word": "left",
            "count": "2,913"
        },
        {
            "word": "forms",
            "count": "2,906"
        },
        {
            "word": "output_dir",
            "count": "2,903"
        },
        {
            "word": "VERBATIM",
            "count": "2,902"
        },
        {
            "word": "conversion",
            "count": "2,897"
        },
        {
            "word": "opencv",
            "count": "2,897"
        },
        {
            "word": "get_target_property",
            "count": "2,895"
        },
        {
            "word": "ARCH",
            "count": "2,893"
        },
        {
            "word": "mode",
            "count": "2,888"
        },
        {
            "word": "True",
            "count": "2,884"
        },
        {
            "word": "CMAKE_INSTALL_LOCAL_ONLY",
            "count": "2,880"
        },
        {
            "word": "SHARED",
            "count": "2,874"
        },
        {
            "word": "PkgConfig",
            "count": "2,873"
        },
        {
            "word": "SDL2_LIBRARY_TEMP",
            "count": "2,858"
        },
        {
            "word": "functions",
            "count": "2,852"
        },
        {
            "word": "builds",
            "count": "2,850"
        },
        {
            "word": "supported",
            "count": "2,850"
        },
        {
            "word": "order",
            "count": "2,837"
        },
        {
            "word": "generating",
            "count": "2,836"
        },
        {
            "word": "CMAKE_CURRENT_LIST_LINE",
            "count": "2,831"
        },
        {
            "word": "API",
            "count": "2,829"
        },
        {
            "word": "built",
            "count": "2,827"
        },
        {
            "word": "GLOBAL",
            "count": "2,819"
        },
        {
            "word": "clang",
            "count": "2,816"
        },
        {
            "word": "different",
            "count": "2,812"
        },
        {
            "word": "Could",
            "count": "2,811"
        },
        {
            "word": "On",
            "count": "2,811"
        },
        {
            "word": "accompanying",
            "count": "2,803"
        },
        {
            "word": "PROJECT_NAME",
            "count": "2,800"
        },
        {
            "word": "std",
            "count": "2,797"
        },
        {
            "word": "Create",
            "count": "2,796"
        },
        {
            "word": "what",
            "count": "2,795"
        },
        {
            "word": "subdirectory",
            "count": "2,793"
        },
        {
            "word": "CMAKE_C_COMPILER",
            "count": "2,788"
        },
        {
            "word": "platforms",
            "count": "2,772"
        },
        {
            "word": "passed",
            "count": "2,771"
        },
        {
            "word": "Force",
            "count": "2,766"
        },
        {
            "word": "Boost_FOUND",
            "count": "2,754"
        },
        {
            "word": "CMAKE_FILES_DIRECTORY",
            "count": "2,740"
        },
        {
            "word": "RELEASE",
            "count": "2,739"
        },
        {
            "word": "DEFAULT_MSG",
            "count": "2,738"
        },
        {
            "word": "DIRECTORY",
            "count": "2,735"
        },
        {
            "word": "general",
            "count": "2,719"
        },
        {
            "word": "extProjName",
            "count": "2,717"
        },
        {
            "word": "tested",
            "count": "2,717"
        },
        {
            "word": "compilation",
            "count": "2,715"
        },
        {
            "word": "_library",
            "count": "2,714"
        },
        {
            "word": "Make",
            "count": "2,711"
        },
        {
            "word": "Studio",
            "count": "2,708"
        },
        {
            "word": "Found",
            "count": "2,702"
        },
        {
            "word": "Compiler",
            "count": "2,696"
        },
        {
            "word": "URL",
            "count": "2,687"
        },
        {
            "word": "RelWithDebInfo",
            "count": "2,683"
        },
        {
            "word": "X11",
            "count": "2,682"
        },
        {
            "word": "results",
            "count": "2,682"
        },
        {
            "word": "xml",
            "count": "2,675"
        },
        {
            "word": "ABI",
            "count": "2,668"
        },
        {
            "word": "point",
            "count": "2,668"
        },
        {
            "word": "scripts",
            "count": "2,667"
        },
        {
            "word": "help",
            "count": "2,662"
        },
        {
            "word": "STATIC",
            "count": "2,660"
        },
        {
            "word": "depend",
            "count": "2,643"
        },
        {
            "word": "Test",
            "count": "2,642"
        },
        {
            "word": "_targetName",
            "count": "2,640"
        },
        {
            "word": "Default",
            "count": "2,633"
        },
        {
            "word": "fail",
            "count": "2,626"
        },
        {
            "word": "key",
            "count": "2,623"
        },
        {
            "word": "self",
            "count": "2,617"
        },
        {
            "word": "COMMENT",
            "count": "2,614"
        },
        {
            "word": "OGRE",
            "count": "2,614"
        },
        {
            "word": "sdk",
            "count": "2,611"
        },
        {
            "word": "OpenGL",
            "count": "2,610"
        },
        {
            "word": "warning",
            "count": "2,610"
        },
        {
            "word": "blank",
            "count": "2,606"
        },
        {
            "word": "OSX",
            "count": "2,604"
        },
        {
            "word": "SOURCES",
            "count": "2,601"
        },
        {
            "word": "current",
            "count": "2,594"
        },
        {
            "word": "FIND_PACKAGE",
            "count": "2,593"
        },
        {
            "word": "LLVM",
            "count": "2,583"
        },
        {
            "word": "TODO",
            "count": "2,576"
        },
        {
            "word": "GLOB",
            "count": "2,568"
        },
        {
            "word": "P",
            "count": "2,566"
        },
        {
            "word": "compatibility",
            "count": "2,565"
        },
        {
            "word": "coverage",
            "count": "2,564"
        },
        {
            "word": "off",
            "count": "2,562"
        },
        {
            "word": "Enable",
            "count": "2,556"
        },
        {
            "word": "than",
            "count": "2,554"
        },
        {
            "word": "apps",
            "count": "2,553"
        },
        {
            "word": "SOURCE",
            "count": "2,551"
        },
        {
            "word": "architecture",
            "count": "2,548"
        },
        {
            "word": "suffix",
            "count": "2,548"
        },
        {
            "word": "force",
            "count": "2,539"
        },
        {
            "word": "Fortran",
            "count": "2,534"
        },
        {
            "word": "When",
            "count": "2,534"
        },
        {
            "word": "expressions",
            "count": "2,533"
        },
        {
            "word": "ENDFUNCTION",
            "count": "2,532"
        },
        {
            "word": "keywords",
            "count": "2,520"
        },
        {
            "word": "CMakeCCompiler",
            "count": "2,518"
        },
        {
            "word": "MATCH",
            "count": "2,518"
        },
        {
            "word": "unity",
            "count": "2,516"
        },
        {
            "word": "Cellar",
            "count": "2,504"
        },
        {
            "word": "VARIABLE",
            "count": "2,503"
        },
        {
            "word": "absolute",
            "count": "2,499"
        },
        {
            "word": "CONFIGURATIONS",
            "count": "2,498"
        },
        {
            "word": "SFML",
            "count": "2,477"
        },
        {
            "word": "property",
            "count": "2,475"
        },
        {
            "word": "add_dependencies",
            "count": "2,473"
        },
        {
            "word": "COMMON",
            "count": "2,471"
        },
        {
            "word": "format",
            "count": "2,467"
        },
        {
            "word": "manually",
            "count": "2,461"
        },
        {
            "word": "corresponding",
            "count": "2,458"
        },
        {
            "word": "ANDROID_NATIVE_API_LEVEL",
            "count": "2,457"
        },
        {
            "word": "disable",
            "count": "2,450"
        },
        {
            "word": "graphics",
            "count": "2,445"
        },
        {
            "word": "NEVER",
            "count": "2,442"
        },
        {
            "word": "RPATH",
            "count": "2,441"
        },
        {
            "word": "add_library",
            "count": "2,440"
        },
        {
            "word": "item",
            "count": "2,435"
        },
        {
            "word": "DEBUG",
            "count": "2,432"
        },
        {
            "word": "check_include_file",
            "count": "2,432"
        },
        {
            "word": "during",
            "count": "2,431"
        },
        {
            "word": "again",
            "count": "2,428"
        },
        {
            "word": "object",
            "count": "2,422"
        },
        {
            "word": "Testfile",
            "count": "2,420"
        },
        {
            "word": "match",
            "count": "2,419"
        },
        {
            "word": "HEADER",
            "count": "2,418"
        },
        {
            "word": "newer",
            "count": "2,414"
        },
        {
            "word": "_boost_COMPILER",
            "count": "2,413"
        },
        {
            "word": "itk",
            "count": "2,407"
        },
        {
            "word": "NAME_WE",
            "count": "2,401"
        },
        {
            "word": "exceptions",
            "count": "2,399"
        },
        {
            "word": "entry",
            "count": "2,398"
        },
        {
            "word": "text",
            "count": "2,395"
        },
        {
            "word": "args",
            "count": "2,390"
        },
        {
            "word": "__availableToolchains",
            "count": "2,385"
        },
        {
            "word": "_argn",
            "count": "2,376"
        },
        {
            "word": "re",
            "count": "2,376"
        },
        {
            "word": "call",
            "count": "2,373"
        },
        {
            "word": "_file",
            "count": "2,371"
        },
        {
            "word": "OPTIONAL",
            "count": "2,368"
        },
        {
            "word": "CMAKE_EXTRA_INCLUDE_FILES",
            "count": "2,364"
        },
        {
            "word": "OPTIONS",
            "count": "2,363"
        },
        {
            "word": "automatically",
            "count": "2,363"
        },
        {
            "word": "ERROR_QUIET",
            "count": "2,362"
        },
        {
            "word": "PYTHON_EXECUTABLE",
            "count": "2,362"
        },
        {
            "word": "dep",
            "count": "2,362"
        },
        {
            "word": "possible",
            "count": "2,357"
        },
        {
            "word": "extension",
            "count": "2,354"
        },
        {
            "word": "app",
            "count": "2,337"
        },
        {
            "word": "CMakeSystem",
            "count": "2,334"
        },
        {
            "word": "packages",
            "count": "2,333"
        },
        {
            "word": "none",
            "count": "2,325"
        },
        {
            "word": "size",
            "count": "2,322"
        },
        {
            "word": "IMPORTED_CONFIGURATIONS",
            "count": "2,321"
        },
        {
            "word": "CMAKE_EXE_LINKER_FLAGS",
            "count": "2,316"
        },
        {
            "word": "CMakeCXXCompiler",
            "count": "2,312"
        },
        {
            "word": "BUILD_SHARED_LIBS",
            "count": "2,309"
        },
        {
            "word": "_DIR",
            "count": "2,309"
        },
        {
            "word": "old",
            "count": "2,305"
        },
        {
            "word": "TYPE",
            "count": "2,304"
        },
        {
            "word": "hunter_add_version",
            "count": "2,301"
        },
        {
            "word": "EXECUTE_PROCESS",
            "count": "2,297"
        },
        {
            "word": "MY_CHECK_TYPE_SIZE",
            "count": "2,293"
        },
        {
            "word": "native",
            "count": "2,293"
        },
        {
            "word": "tool",
            "count": "2,291"
        },
        {
            "word": "export",
            "count": "2,287"
        },
        {
            "word": "over",
            "count": "2,286"
        },
        {
            "word": "L",
            "count": "2,284"
        },
        {
            "word": "Relative",
            "count": "2,284"
        },
        {
            "word": "THE",
            "count": "2,284"
        },
        {
            "word": "REMOVE_ITEM",
            "count": "2,281"
        },
        {
            "word": "CMAKE_MATCH_1",
            "count": "2,278"
        },
        {
            "word": "OpenCV",
            "count": "2,278"
        },
        {
            "word": "CHECK_SYMBOL_EXISTS",
            "count": "2,277"
        },
        {
            "word": "OGRE_",
            "count": "2,274"
        },
        {
            "word": "Generating",
            "count": "2,271"
        },
        {
            "word": "know",
            "count": "2,269"
        },
        {
            "word": "public",
            "count": "2,267"
        },
        {
            "word": "GCC",
            "count": "2,263"
        },
        {
            "word": "projects",
            "count": "2,260"
        },
        {
            "word": "sh",
            "count": "2,259"
        },
        {
            "word": "_sourceFiles",
            "count": "2,251"
        },
        {
            "word": "CMAKE_CXX_INCLUDE_REGEX_COMPLAIN",
            "count": "2,244"
        },
        {
            "word": "CMAKE_CXX_INCLUDE_REGEX_SCAN",
            "count": "2,244"
        },
        {
            "word": "internal",
            "count": "2,240"
        },
        {
            "word": "CMAKE_COMPILER_IS_MINGW",
            "count": "2,239"
        },
        {
            "word": "CMAKE_FORCE_UNIX_PATHS",
            "count": "2,233"
        },
        {
            "word": "classes",
            "count": "2,232"
        },
        {
            "word": "_IMPORT_CHECK_TARGETS",
            "count": "2,231"
        },
        {
            "word": "ARGC",
            "count": "2,230"
        },
        {
            "word": "CMAKE_REQUIRED_FLAGS",
            "count": "2,230"
        },
        {
            "word": "hydro",
            "count": "2,230"
        },
        {
            "word": "patch",
            "count": "2,225"
        },
        {
            "word": "zlib",
            "count": "2,223"
        },
        {
            "word": "OF",
            "count": "2,219"
        },
        {
            "word": "page",
            "count": "2,219"
        },
        {
            "word": "QtCore",
            "count": "2,216"
        },
        {
            "word": "Mac",
            "count": "2,215"
        },
        {
            "word": "SimplexLP",
            "count": "2,210"
        },
        {
            "word": "cmeon",
            "count": "2,210"
        },
        {
            "word": "_prefixFile",
            "count": "2,206"
        },
        {
            "word": "ROOT_BUILD_OPTION",
            "count": "2,204"
        },
        {
            "word": "rst",
            "count": "2,203"
        },
        {
            "word": "multiple",
            "count": "2,200"
        },
        {
            "word": "inc",
            "count": "2,198"
        },
        {
            "word": "BOOST_ROOT",
            "count": "2,197"
        },
        {
            "word": "ANDROID_ARCH_NAME",
            "count": "2,193"
        },
        {
            "word": "contains",
            "count": "2,193"
        },
        {
            "word": "dot",
            "count": "2,187"
        },
        {
            "word": "CMAKE_REQUIRED_INCLUDES",
            "count": "2,179"
        },
        {
            "word": "cuda_execute_process",
            "count": "2,179"
        },
        {
            "word": "LATEX_TARGET",
            "count": "2,175"
        },
        {
            "word": "QT_",
            "count": "2,175"
        },
        {
            "word": "nvcc_host_compiler_flags",
            "count": "2,175"
        },
        {
            "word": "imported",
            "count": "2,163"
        },
        {
            "word": "v7a",
            "count": "2,161"
        },
        {
            "word": "Look",
            "count": "2,156"
        },
        {
            "word": "man",
            "count": "2,154"
        },
        {
            "word": "arch",
            "count": "2,151"
        },
        {
            "word": "bindings",
            "count": "2,151"
        },
        {
            "word": "ANDROID_NDK_ABI_NAME",
            "count": "2,150"
        },
        {
            "word": "CMAKE_CROSSCOMPILING",
            "count": "2,150"
        },
        {
            "word": "checks",
            "count": "2,150"
        },
        {
            "word": "LaTeX",
            "count": "2,147"
        },
        {
            "word": "_msg",
            "count": "2,147"
        },
        {
            "word": "MinGW",
            "count": "2,145"
        },
        {
            "word": "CMAKE_COMPILER_IS_CYGWIN",
            "count": "2,144"
        },
        {
            "word": "CMAKE_CONFIGURATION_TYPES",
            "count": "2,143"
        },
        {
            "word": "find_package_handle_standard_args",
            "count": "2,138"
        },
        {
            "word": "hunter_config",
            "count": "2,138"
        },
        {
            "word": "PLUGIN",
            "count": "2,136"
        },
        {
            "word": "including",
            "count": "2,134"
        },
        {
            "word": "modify",
            "count": "2,133"
        },
        {
            "word": "CMAKE_FIND_LIBRARY_SUFFIXES",
            "count": "2,130"
        },
        {
            "word": "itself",
            "count": "2,124"
        },
        {
            "word": "BLAS_LIBRARIES",
            "count": "2,117"
        },
        {
            "word": "CMAKE_DEPENDS_CHECK_C",
            "count": "2,112"
        },
        {
            "word": "_item",
            "count": "2,112"
        },
        {
            "word": "base",
            "count": "2,108"
        },
        {
            "word": "Get",
            "count": "2,107"
        },
        {
            "word": "deprecated",
            "count": "2,106"
        },
        {
            "word": "once",
            "count": "2,105"
        },
        {
            "word": "undef",
            "count": "2,102"
        },
        {
            "word": "precompiled",
            "count": "2,100"
        },
        {
            "word": "POST_BUILD",
            "count": "2,097"
        },
        {
            "word": "REMOVE_DUPLICATES",
            "count": "2,095"
        },
        {
            "word": "compiled",
            "count": "2,094"
        },
        {
            "word": "CMAKE_FIND_ROOT_PATH_MODE_INCLUDE",
            "count": "2,093"
        },
        {
            "word": "obj",
            "count": "2,093"
        },
        {
            "word": "ExternalProject_Add",
            "count": "2,090"
        },
        {
            "word": "hash",
            "count": "2,089"
        },
        {
            "word": "regex",
            "count": "2,089"
        },
        {
            "word": "ifndef",
            "count": "2,088"
        },
        {
            "word": "status",
            "count": "2,086"
        },
        {
            "word": "z",
            "count": "2,086"
        },
        {
            "word": "ITK",
            "count": "2,085"
        },
        {
            "word": "being",
            "count": "2,084"
        },
        {
            "word": "LIBRARIES",
            "count": "2,082"
        },
        {
            "word": "CMAKE_FIND_ROOT_PATH_MODE_LIBRARY",
            "count": "2,077"
        },
        {
            "word": "caller",
            "count": "2,077"
        },
        {
            "word": "Flags",
            "count": "2,076"
        },
        {
            "word": "description",
            "count": "2,075"
        },
        {
            "word": "CMAKE_CXX_FLAGS_DEBUG",
            "count": "2,074"
        },
        {
            "word": "infile",
            "count": "2,070"
        },
        {
            "word": "keyword",
            "count": "2,068"
        },
        {
            "word": "Example",
            "count": "2,067"
        },
        {
            "word": "READ",
            "count": "2,065"
        },
        {
            "word": "CMakeParseArguments",
            "count": "2,061"
        },
        {
            "word": "members",
            "count": "2,059"
        },
        {
            "word": "BLA_VENDOR",
            "count": "2,058"
        },
        {
            "word": "CMAKE_FIND_ROOT_PATH_MODE_PROGRAM",
            "count": "2,058"
        },
        {
            "word": "ANDROID_STL",
            "count": "2,057"
        },
        {
            "word": "def",
            "count": "2,049"
        },
        {
            "word": "filter",
            "count": "2,048"
        },
        {
            "word": "INSTALL_DIR",
            "count": "2,041"
        },
        {
            "word": "pcl",
            "count": "2,036"
        },
        {
            "word": "typedef",
            "count": "2,032"
        },
        {
            "word": "STRINGS",
            "count": "2,031"
        },
        {
            "word": "exists",
            "count": "2,031"
        },
        {
            "word": "Arduino",
            "count": "2,030"
        },
        {
            "word": "ifdef",
            "count": "2,028"
        },
        {
            "word": "Boost_INCLUDE_DIR",
            "count": "2,026"
        },
        {
            "word": "needs",
            "count": "2,024"
        },
        {
            "word": "parameter",
            "count": "2,024"
        },
        {
            "word": "lua",
            "count": "2,023"
        },
        {
            "word": "otherwise",
            "count": "2,022"
        }
    ]
}