{
    "language": "py",
    "words": [
        {
            "word": "self",
            "count": "89,273,871"
        },
        {
            "word": "if",
            "count": "28,920,253"
        },
        {
            "word": "def",
            "count": "28,015,213"
        },
        {
            "word": "return",
            "count": "23,106,623"
        },
        {
            "word": "import",
            "count": "21,428,420"
        },
        {
            "word": "the",
            "count": "20,831,947"
        },
        {
            "word": "in",
            "count": "16,509,664"
        },
        {
            "word": "None",
            "count": "15,218,582"
        },
        {
            "word": "for",
            "count": "14,572,364"
        },
        {
            "word": "from",
            "count": "13,616,950"
        },
        {
            "word": "True",
            "count": "12,846,280"
        },
        {
            "word": "a",
            "count": "11,585,045"
        },
        {
            "word": "to",
            "count": "11,530,875"
        },
        {
            "word": "is",
            "count": "11,213,755"
        },
        {
            "word": "else",
            "count": "11,205,881"
        },
        {
            "word": "not",
            "count": "10,110,382"
        },
        {
            "word": "s",
            "count": "10,037,375"
        },
        {
            "word": "name",
            "count": "9,126,438"
        },
        {
            "word": "of",
            "count": "8,522,581"
        },
        {
            "word": "False",
            "count": "7,742,598"
        },
        {
            "word": "and",
            "count": "7,702,834"
        },
        {
            "word": "django",
            "count": "5,793,025"
        },
        {
            "word": "try",
            "count": "5,787,311"
        },
        {
            "word": "except",
            "count": "5,429,728"
        },
        {
            "word": "value",
            "count": "5,402,822"
        },
        {
            "word": "class",
            "count": "5,339,272"
        },
        {
            "word": "as",
            "count": "5,325,673"
        },
        {
            "word": "data",
            "count": "5,297,927"
        },
        {
            "word": "x",
            "count": "5,270,509"
        },
        {
            "word": "db",
            "count": "5,220,297"
        },
        {
            "word": "path",
            "count": "5,171,957"
        },
        {
            "word": "models",
            "count": "5,170,986"
        },
        {
            "word": "id",
            "count": "5,048,910"
        },
        {
            "word": "os",
            "count": "5,000,030"
        },
        {
            "word": "fields",
            "count": "4,665,629"
        },
        {
            "word": "assertEqual",
            "count": "4,503,764"
        },
        {
            "word": "with",
            "count": "4,422,458"
        },
        {
            "word": "context",
            "count": "4,377,148"
        },
        {
            "word": "or",
            "count": "4,286,546"
        },
        {
            "word": "type",
            "count": "4,219,633"
        },
        {
            "word": "n",
            "count": "4,066,498"
        },
        {
            "word": "get",
            "count": "3,976,980"
        },
        {
            "word": "i",
            "count": "3,925,283"
        },
        {
            "word": "be",
            "count": "3,770,736"
        },
        {
            "word": "args",
            "count": "3,752,965"
        },
        {
            "word": "raise",
            "count": "3,475,001"
        },
        {
            "word": "len",
            "count": "3,311,106"
        },
        {
            "word": "request",
            "count": "3,280,326"
        },
        {
            "word": "result",
            "count": "3,276,288"
        },
        {
            "word": "r",
            "count": "3,275,377"
        },
        {
            "word": "append",
            "count": "3,241,598"
        },
        {
            "word": "default",
            "count": "3,214,838"
        },
        {
            "word": "cls",
            "count": "3,190,143"
        },
        {
            "word": "param",
            "count": "3,169,229"
        },
        {
            "word": "this",
            "count": "3,149,048"
        },
        {
            "word": "ns3",
            "count": "3,144,760"
        },
        {
            "word": "f",
            "count": "3,094,635"
        },
        {
            "word": "__init__",
            "count": "3,064,412"
        },
        {
            "word": "sys",
            "count": "3,051,976"
        },
        {
            "word": "that",
            "count": "3,049,828"
        },
        {
            "word": "file",
            "count": "2,907,954"
        },
        {
            "word": "The",
            "count": "2,852,448"
        },
        {
            "word": "t",
            "count": "2,820,875"
        },
        {
            "word": "u",
            "count": "2,816,832"
        },
        {
            "word": "key",
            "count": "2,786,643"
        },
        {
            "word": "e",
            "count": "2,772,126"
        },
        {
            "word": "pass",
            "count": "2,742,017"
        },
        {
            "word": "list",
            "count": "2,726,941"
        },
        {
            "word": "user",
            "count": "2,725,652"
        },
        {
            "word": "response",
            "count": "2,715,548"
        },
        {
            "word": "module",
            "count": "2,673,283"
        },
        {
            "word": "print",
            "count": "2,621,875"
        },
        {
            "word": "d",
            "count": "2,587,118"
        },
        {
            "word": "object",
            "count": "2,551,301"
        },
        {
            "word": "_",
            "count": "2,490,392"
        },
        {
            "word": "instance",
            "count": "2,474,257"
        },
        {
            "word": "kwargs",
            "count": "2,413,010"
        },
        {
            "word": "elif",
            "count": "2,377,934"
        },
        {
            "word": "str",
            "count": "2,313,274"
        },
        {
            "word": "b",
            "count": "2,295,023"
        },
        {
            "word": "time",
            "count": "2,260,952"
        },
        {
            "word": "c",
            "count": "2,257,532"
        },
        {
            "word": "line",
            "count": "2,215,705"
        },
        {
            "word": "it",
            "count": "2,154,379"
        },
        {
            "word": "are",
            "count": "2,150,427"
        },
        {
            "word": "url",
            "count": "2,145,173"
        },
        {
            "word": "an",
            "count": "2,089,744"
        },
        {
            "word": "assert",
            "count": "2,075,346"
        },
        {
            "word": "text",
            "count": "2,048,534"
        },
        {
            "word": "test",
            "count": "2,030,236"
        },
        {
            "word": "np",
            "count": "2,013,223"
        },
        {
            "word": "on",
            "count": "2,011,675"
        },
        {
            "word": "set",
            "count": "1,982,341"
        },
        {
            "word": "p",
            "count": "1,939,960"
        },
        {
            "word": "int",
            "count": "1,903,909"
        },
        {
            "word": "If",
            "count": "1,887,680"
        },
        {
            "word": "string",
            "count": "1,886,652"
        },
        {
            "word": "y",
            "count": "1,884,447"
        },
        {
            "word": "h",
            "count": "1,874,416"
        },
        {
            "word": "function",
            "count": "1,865,207"
        },
        {
            "word": "node",
            "count": "1,826,210"
        },
        {
            "word": "config",
            "count": "1,798,439"
        },
        {
            "word": "res",
            "count": "1,785,764"
        },
        {
            "word": "by",
            "count": "1,777,665"
        },
        {
            "word": "error",
            "count": "1,756,106"
        },
        {
            "word": "This",
            "count": "1,737,644"
        },
        {
            "word": "all",
            "count": "1,725,213"
        },
        {
            "word": "join",
            "count": "1,681,105"
        },
        {
            "word": "will",
            "count": "1,668,939"
        },
        {
            "word": "msg",
            "count": "1,646,307"
        },
        {
            "word": "options",
            "count": "1,614,832"
        },
        {
            "word": "version",
            "count": "1,585,846"
        },
        {
            "word": "status",
            "count": "1,573,662"
        },
        {
            "word": "datetime",
            "count": "1,571,962"
        },
        {
            "word": "we",
            "count": "1,570,732"
        },
        {
            "word": "values",
            "count": "1,553,175"
        },
        {
            "word": "A",
            "count": "1,546,286"
        },
        {
            "word": "max_length",
            "count": "1,544,200"
        },
        {
            "word": "message",
            "count": "1,520,442"
        },
        {
            "word": "client",
            "count": "1,515,374"
        },
        {
            "word": "write",
            "count": "1,511,024"
        },
        {
            "word": "objects",
            "count": "1,504,138"
        },
        {
            "word": "utf",
            "count": "1,496,263"
        },
        {
            "word": "obj",
            "count": "1,494,636"
        },
        {
            "word": "dict",
            "count": "1,492,857"
        },
        {
            "word": "method",
            "count": "1,483,847"
        },
        {
            "word": "index",
            "count": "1,470,305"
        },
        {
            "word": "m",
            "count": "1,440,660"
        },
        {
            "word": "isinstance",
            "count": "1,440,190"
        },
        {
            "word": "output",
            "count": "1,422,885"
        },
        {
            "word": "env",
            "count": "1,410,026"
        },
        {
            "word": "close",
            "count": "1,402,539"
        },
        {
            "word": "__name__",
            "count": "1,396,125"
        },
        {
            "word": "other",
            "count": "1,382,405"
        },
        {
            "word": "json",
            "count": "1,370,012"
        },
        {
            "word": "continue",
            "count": "1,364,676"
        },
        {
            "word": "CharField",
            "count": "1,362,138"
        },
        {
            "word": "code",
            "count": "1,359,695"
        },
        {
            "word": "v",
            "count": "1,357,270"
        },
        {
            "word": "field",
            "count": "1,351,965"
        },
        {
            "word": "model",
            "count": "1,341,221"
        },
        {
            "word": "add_method",
            "count": "1,335,890"
        },
        {
            "word": "filename",
            "count": "1,334,164"
        },
        {
            "word": "params",
            "count": "1,323,751"
        },
        {
            "word": "logging",
            "count": "1,313,332"
        },
        {
            "word": "property",
            "count": "1,309,196"
        },
        {
            "word": "re",
            "count": "1,308,419"
        },
        {
            "word": "http",
            "count": "1,305,830"
        },
        {
            "word": "use",
            "count": "1,296,361"
        },
        {
            "word": "item",
            "count": "1,295,698"
        },
        {
            "word": "out",
            "count": "1,274,625"
        },
        {
            "word": "session",
            "count": "1,270,385"
        },
        {
            "word": "core",
            "count": "1,261,136"
        },
        {
            "word": "start",
            "count": "1,258,508"
        },
        {
            "word": "size",
            "count": "1,256,996"
        },
        {
            "word": "Exception",
            "count": "1,255,579"
        },
        {
            "word": "utils",
            "count": "1,250,589"
        },
        {
            "word": "can",
            "count": "1,250,129"
        },
        {
            "word": "format",
            "count": "1,240,459"
        },
        {
            "word": "range",
            "count": "1,237,766"
        },
        {
            "word": "settings",
            "count": "1,235,172"
        },
        {
            "word": "blank",
            "count": "1,233,365"
        },
        {
            "word": "host",
            "count": "1,217,171"
        },
        {
            "word": "state",
            "count": "1,212,103"
        },
        {
            "word": "k",
            "count": "1,208,700"
        },
        {
            "word": "info",
            "count": "1,202,530"
        },
        {
            "word": "python",
            "count": "1,196,598"
        },
        {
            "word": "body",
            "count": "1,188,748"
        },
        {
            "word": "com",
            "count": "1,183,262"
        },
        {
            "word": "no",
            "count": "1,181,949"
        },
        {
            "word": "should",
            "count": "1,178,769"
        },
        {
            "word": "mock",
            "count": "1,173,070"
        },
        {
            "word": "title",
            "count": "1,164,647"
        },
        {
            "word": "used",
            "count": "1,160,660"
        },
        {
            "word": "network",
            "count": "1,157,189"
        },
        {
            "word": "log",
            "count": "1,155,727"
        },
        {
            "word": "Returns",
            "count": "1,150,489"
        },
        {
            "word": "files",
            "count": "1,147,802"
        },
        {
            "word": "update",
            "count": "1,123,822"
        },
        {
            "word": "coding",
            "count": "1,120,565"
        },
        {
            "word": "create",
            "count": "1,118,805"
        },
        {
            "word": "query",
            "count": "1,112,112"
        },
        {
            "word": "ValueError",
            "count": "1,098,490"
        },
        {
            "word": "break",
            "count": "1,083,348"
        },
        {
            "word": "group",
            "count": "1,080,953"
        },
        {
            "word": "description",
            "count": "1,073,385"
        },
        {
            "word": "exception",
            "count": "1,072,541"
        },
        {
            "word": "req",
            "count": "1,066,650"
        },
        {
            "word": "array",
            "count": "1,058,581"
        },
        {
            "word": "const",
            "count": "1,056,095"
        },
        {
            "word": "action",
            "count": "1,052,278"
        },
        {
            "word": "content",
            "count": "1,046,805"
        },
        {
            "word": "form",
            "count": "1,040,061"
        },
        {
            "word": "source",
            "count": "1,034,856"
        },
        {
            "word": "cr",
            "count": "1,034,384"
        },
        {
            "word": "add",
            "count": "1,021,953"
        },
        {
            "word": "app",
            "count": "1,017,519"
        },
        {
            "word": "read",
            "count": "1,006,935"
        },
        {
            "word": "while",
            "count": "1,003,520"
        },
        {
            "word": "port",
            "count": "1,002,903"
        },
        {
            "word": "parser",
            "count": "998,354"
        },
        {
            "word": "bin",
            "count": "992,530"
        },
        {
            "word": "uid",
            "count": "978,061"
        },
        {
            "word": "parent",
            "count": "968,328"
        },
        {
            "word": "number",
            "count": "961,872"
        },
        {
            "word": "x00",
            "count": "955,687"
        },
        {
            "word": "event",
            "count": "943,804"
        },
        {
            "word": "count",
            "count": "942,565"
        },
        {
            "word": "image",
            "count": "940,653"
        },
        {
            "word": "server",
            "count": "937,050"
        },
        {
            "word": "new",
            "count": "936,869"
        },
        {
            "word": "headers",
            "count": "936,704"
        },
        {
            "word": "member",
            "count": "934,662"
        },
        {
            "word": "usr",
            "count": "930,732"
        },
        {
            "word": "run",
            "count": "926,749"
        },
        {
            "word": "split",
            "count": "926,665"
        },
        {
            "word": "which",
            "count": "923,118"
        },
        {
            "word": "open",
            "count": "918,618"
        },
        {
            "word": "table",
            "count": "916,922"
        },
        {
            "word": "main",
            "count": "901,068"
        },
        {
            "word": "have",
            "count": "894,949"
        },
        {
            "word": "html",
            "count": "889,772"
        },
        {
            "word": "match",
            "count": "887,670"
        },
        {
            "word": "api",
            "count": "887,502"
        },
        {
            "word": "page",
            "count": "884,299"
        },
        {
            "word": "project",
            "count": "878,978"
        },
        {
            "word": "base",
            "count": "878,379"
        },
        {
            "word": "save",
            "count": "871,843"
        },
        {
            "word": "void",
            "count": "869,411"
        },
        {
            "word": "bool",
            "count": "867,845"
        },
        {
            "word": "null",
            "count": "867,700"
        },
        {
            "word": "items",
            "count": "864,953"
        },
        {
            "word": "copy",
            "count": "860,170"
        },
        {
            "word": "one",
            "count": "857,137"
        },
        {
            "word": "debug",
            "count": "853,146"
        },
        {
            "word": "__main__",
            "count": "850,989"
        },
        {
            "word": "X",
            "count": "848,620"
        },
        {
            "word": "when",
            "count": "844,707"
        },
        {
            "word": "assertRaises",
            "count": "843,195"
        },
        {
            "word": "foo",
            "count": "834,542"
        },
        {
            "word": "w",
            "count": "834,020"
        },
        {
            "word": "command",
            "count": "823,152"
        },
        {
            "word": "end",
            "count": "822,378"
        },
        {
            "word": "password",
            "count": "822,056"
        },
        {
            "word": "only",
            "count": "821,367"
        },
        {
            "word": "g",
            "count": "819,404"
        },
        {
            "word": "target",
            "count": "818,368"
        },
        {
            "word": "tag",
            "count": "814,938"
        },
        {
            "word": "address",
            "count": "811,800"
        },
        {
            "word": "any",
            "count": "809,405"
        },
        {
            "word": "at",
            "count": "809,197"
        },
        {
            "word": "label",
            "count": "804,310"
        },
        {
            "word": "logger",
            "count": "801,106"
        },
        {
            "word": "auth",
            "count": "800,327"
        },
        {
            "word": "expected",
            "count": "794,887"
        },
        {
            "word": "patch",
            "count": "792,304"
        },
        {
            "word": "assertTrue",
            "count": "791,780"
        },
        {
            "word": "row",
            "count": "790,528"
        },
        {
            "word": "current",
            "count": "786,002"
        },
        {
            "word": "results",
            "count": "779,713"
        },
        {
            "word": "username",
            "count": "769,467"
        },
        {
            "word": "so",
            "count": "769,326"
        },
        {
            "word": "first",
            "count": "762,502"
        },
        {
            "word": "contrib",
            "count": "760,563"
        },
        {
            "word": "val",
            "count": "758,984"
        },
        {
            "word": "mode",
            "count": "755,619"
        },
        {
            "word": "exit",
            "count": "753,945"
        },
        {
            "word": "input",
            "count": "743,558"
        },
        {
            "word": "level",
            "count": "741,053"
        },
        {
            "word": "template",
            "count": "738,352"
        },
        {
            "word": "lambda",
            "count": "732,718"
        },
        {
            "word": "numpy",
            "count": "729,532"
        },
        {
            "word": "connection",
            "count": "728,108"
        },
        {
            "word": "primary_key",
            "count": "721,877"
        },
        {
            "word": "exists",
            "count": "721,401"
        },
        {
            "word": "unittest",
            "count": "719,190"
        },
        {
            "word": "has",
            "count": "719,044"
        },
        {
            "word": "directory",
            "count": "718,384"
        },
        {
            "word": "must",
            "count": "717,642"
        },
        {
            "word": "resp",
            "count": "715,371"
        },
        {
            "word": "check",
            "count": "713,922"
        },
        {
            "word": "super",
            "count": "712,751"
        },
        {
            "word": "uuid",
            "count": "709,049"
        },
        {
            "word": "help",
            "count": "708,259"
        },
        {
            "word": "true",
            "count": "707,530"
        },
        {
            "word": "required",
            "count": "695,623"
        },
        {
            "word": "cmd",
            "count": "694,797"
        },
        {
            "word": "shape",
            "count": "690,088"
        },
        {
            "word": "you",
            "count": "688,893"
        },
        {
            "word": "email",
            "count": "688,765"
        },
        {
            "word": "call",
            "count": "687,251"
        },
        {
            "word": "l",
            "count": "686,157"
        },
        {
            "word": "given",
            "count": "686,010"
        },
        {
            "word": "volume",
            "count": "680,813"
        },
        {
            "word": "order",
            "count": "679,766"
        },
        {
            "word": "names",
            "count": "677,772"
        },
        {
            "word": "root",
            "count": "677,206"
        },
        {
            "word": "float",
            "count": "676,586"
        },
        {
            "word": "conf",
            "count": "676,581"
        },
        {
            "word": "now",
            "count": "673,575"
        },
        {
            "word": "func",
            "count": "669,341"
        },
        {
            "word": "filter",
            "count": "664,703"
        },
        {
            "word": "keys",
            "count": "663,770"
        },
        {
            "word": "admin",
            "count": "663,649"
        },
        {
            "word": "Meta",
            "count": "662,663"
        },
        {
            "word": "token",
            "count": "659,138"
        },
        {
            "word": "errors",
            "count": "657,464"
        },
        {
            "word": "ret",
            "count": "656,732"
        },
        {
            "word": "socket",
            "count": "655,533"
        },
        {
            "word": "setUp",
            "count": "650,510"
        },
        {
            "word": "here",
            "count": "645,290"
        },
        {
            "word": "status_code",
            "count": "643,045"
        },
        {
            "word": "tests",
            "count": "641,571"
        },
        {
            "word": "classmethod",
            "count": "635,638"
        },
        {
            "word": "User",
            "count": "632,428"
        },
        {
            "word": "C",
            "count": "631,450"
        },
        {
            "word": "conn",
            "count": "627,957"
        },
        {
            "word": "using",
            "count": "622,930"
        },
        {
            "word": "arg",
            "count": "622,458"
        },
        {
            "word": "root_module",
            "count": "621,227"
        },
        {
            "word": "show",
            "count": "620,647"
        },
        {
            "word": "is_const",
            "count": "617,494"
        },
        {
            "word": "record",
            "count": "614,631"
        },
        {
            "word": "__future__",
            "count": "611,148"
        },
        {
            "word": "random",
            "count": "606,264"
        },
        {
            "word": "but",
            "count": "603,929"
        },
        {
            "word": "application",
            "count": "603,809"
        },
        {
            "word": "date",
            "count": "601,705"
        },
        {
            "word": "org",
            "count": "598,112"
        },
        {
            "word": "common",
            "count": "594,975"
        },
        {
            "word": "j",
            "count": "594,196"
        },
        {
            "word": "metadata",
            "count": "592,423"
        },
        {
            "word": "yield",
            "count": "592,121"
        },
        {
            "word": "lines",
            "count": "592,099"
        },
        {
            "word": "Python",
            "count": "591,475"
        },
        {
            "word": "ids",
            "count": "591,236"
        },
        {
            "word": "en",
            "count": "587,949"
        },
        {
            "word": "option",
            "count": "581,558"
        },
        {
            "word": "Test",
            "count": "579,037"
        },
        {
            "word": "dtype",
            "count": "578,485"
        },
        {
            "word": "found",
            "count": "578,215"
        },
        {
            "word": "stdout",
            "count": "574,181"
        },
        {
            "word": "T",
            "count": "567,426"
        },
        {
            "word": "domain",
            "count": "566,911"
        },
        {
            "word": "delete",
            "count": "566,356"
        },
        {
            "word": "AutoField",
            "count": "561,394"
        },
        {
            "word": "execute",
            "count": "561,018"
        },
        {
            "word": "z",
            "count": "560,582"
        },
        {
            "word": "example",
            "count": "554,664"
        },
        {
            "word": "err",
            "count": "553,240"
        },
        {
            "word": "header",
            "count": "552,639"
        },
        {
            "word": "o",
            "count": "551,358"
        },
        {
            "word": "replace",
            "count": "550,264"
        },
        {
            "word": "search",
            "count": "548,909"
        },
        {
            "word": "q",
            "count": "548,787"
        },
        {
            "word": "Add",
            "count": "544,014"
        },
        {
            "word": "service",
            "count": "543,080"
        },
        {
            "word": "entry",
            "count": "541,785"
        },
        {
            "word": "device",
            "count": "539,494"
        },
        {
            "word": "encoding",
            "count": "538,978"
        },
        {
            "word": "into",
            "count": "535,682"
        },
        {
            "word": "argv",
            "count": "535,242"
        },
        {
            "word": "length",
            "count": "535,095"
        },
        {
            "word": "Return",
            "count": "531,936"
        },
        {
            "word": "xml",
            "count": "530,897"
        },
        {
            "word": "py",
            "count": "530,499"
        },
        {
            "word": "cursor",
            "count": "529,954"
        },
        {
            "word": "do",
            "count": "525,995"
        },
        {
            "word": "driver",
            "count": "525,605"
        },
        {
            "word": "remove",
            "count": "525,194"
        },
        {
            "word": "resource",
            "count": "521,545"
        },
        {
            "word": "attr",
            "count": "520,521"
        },
        {
            "word": "prefix",
            "count": "518,923"
        },
        {
            "word": "then",
            "count": "517,163"
        },
        {
            "word": "staticmethod",
            "count": "516,956"
        },
        {
            "word": "post",
            "count": "516,087"
        },
        {
            "word": "each",
            "count": "514,140"
        },
        {
            "word": "task",
            "count": "509,222"
        },
        {
            "word": "Set",
            "count": "508,820"
        },
        {
            "word": "location",
            "count": "506,202"
        },
        {
            "word": "tuple",
            "count": "502,307"
        },
        {
            "word": "strip",
            "count": "502,116"
        },
        {
            "word": "arguments",
            "count": "501,864"
        },
        {
            "word": "part",
            "count": "499,332"
        },
        {
            "word": "timeout",
            "count": "498,714"
        },
        {
            "word": "TypeError",
            "count": "497,934"
        },
        {
            "word": "Parameters",
            "count": "497,042"
        },
        {
            "word": "optional",
            "count": "496,694"
        },
        {
            "word": "returns",
            "count": "496,552"
        },
        {
            "word": "nova",
            "count": "495,913"
        },
        {
            "word": "cfg",
            "count": "495,705"
        },
        {
            "word": "cache",
            "count": "493,794"
        },
        {
            "word": "static",
            "count": "491,060"
        },
        {
            "word": "next",
            "count": "485,413"
        },
        {
            "word": "doc",
            "count": "483,941"
        },
        {
            "word": "sleep",
            "count": "482,608"
        },
        {
            "word": "verbose",
            "count": "481,954"
        },
        {
            "word": "migrations",
            "count": "481,760"
        },
        {
            "word": "return_value",
            "count": "480,340"
        },
        {
            "word": "course",
            "count": "476,905"
        },
        {
            "word": "parameters",
            "count": "476,009"
        },
        {
            "word": "Args",
            "count": "474,831"
        },
        {
            "word": "pool",
            "count": "473,772"
        },
        {
            "word": "find",
            "count": "472,008"
        },
        {
            "word": "up",
            "count": "471,851"
        },
        {
            "word": "reverse",
            "count": "471,672"
        },
        {
            "word": "assert_equal",
            "count": "466,538"
        },
        {
            "word": "pos",
            "count": "466,357"
        },
        {
            "word": "after",
            "count": "464,977"
        },
        {
            "word": "flags",
            "count": "462,298"
        },
        {
            "word": "S",
            "count": "460,631"
        },
        {
            "word": "del",
            "count": "460,187"
        },
        {
            "word": "same",
            "count": "459,045"
        },
        {
            "word": "ctx",
            "count": "457,324"
        },
        {
            "word": "uint32_t",
            "count": "456,666"
        },
        {
            "word": "width",
            "count": "456,462"
        },
        {
            "word": "was",
            "count": "455,628"
        },
        {
            "word": "compute",
            "count": "455,262"
        },
        {
            "word": "getattr",
            "count": "453,104"
        },
        {
            "word": "LOG",
            "count": "452,933"
        },
        {
            "word": "plt",
            "count": "450,528"
        },
        {
            "word": "setup",
            "count": "449,619"
        },
        {
            "word": "hasattr",
            "count": "448,591"
        },
        {
            "word": "For",
            "count": "448,476"
        },
        {
            "word": "configuration",
            "count": "447,539"
        },
        {
            "word": "child",
            "count": "445,291"
        },
        {
            "word": "I",
            "count": "445,138"
        },
        {
            "word": "messages",
            "count": "445,085"
        },
        {
            "word": "pop",
            "count": "444,684"
        },
        {
            "word": "where",
            "count": "443,450"
        },
        {
            "word": "account",
            "count": "442,617"
        },
        {
            "word": "more",
            "count": "440,133"
        },
        {
            "word": "created",
            "count": "438,718"
        },
        {
            "word": "select",
            "count": "437,020"
        },
        {
            "word": "system",
            "count": "436,783"
        },
        {
            "word": "case",
            "count": "436,085"
        },
        {
            "word": "Create",
            "count": "435,735"
        },
        {
            "word": "subprocess",
            "count": "434,897"
        },
        {
            "word": "exc",
            "count": "434,138"
        },
        {
            "word": "DateTimeField",
            "count": "433,607"
        },
        {
            "word": "element",
            "count": "433,572"
        },
        {
            "word": "called",
            "count": "430,578"
        },
        {
            "word": "See",
            "count": "430,386"
        },
        {
            "word": "environ",
            "count": "429,424"
        },
        {
            "word": "attributes",
            "count": "429,319"
        },
        {
            "word": "bar",
            "count": "428,402"
        },
        {
            "word": "offset",
            "count": "426,008"
        },
        {
            "word": "like",
            "count": "423,974"
        },
        {
            "word": "finally",
            "count": "423,749"
        },
        {
            "word": "style",
            "count": "423,507"
        },
        {
            "word": "attribute",
            "count": "422,565"
        },
        {
            "word": "nodes",
            "count": "421,692"
        },
        {
            "word": "column",
            "count": "421,648"
        },
        {
            "word": "assertEquals",
            "count": "421,197"
        },
        {
            "word": "link",
            "count": "420,630"
        },
        {
            "word": "view",
            "count": "420,448"
        },
        {
            "word": "stream",
            "count": "420,297"
        },
        {
            "word": "https",
            "count": "419,585"
        },
        {
            "word": "URL",
            "count": "417,721"
        },
        {
            "word": "specified",
            "count": "416,871"
        },
        {
            "word": "user_id",
            "count": "415,742"
        },
        {
            "word": "object_name",
            "count": "413,963"
        },
        {
            "word": "KeyError",
            "count": "412,938"
        },
        {
            "word": "dirname",
            "count": "412,890"
        },
        {
            "word": "exceptions",
            "count": "410,773"
        },
        {
            "word": "stderr",
            "count": "409,725"
        },
        {
            "word": "does",
            "count": "409,303"
        },
        {
            "word": "forms",
            "count": "408,424"
        },
        {
            "word": "callback",
            "count": "407,602"
        },
        {
            "word": "document",
            "count": "407,300"
        },
        {
            "word": "orm",
            "count": "404,908"
        },
        {
            "word": "ID",
            "count": "401,792"
        },
        {
            "word": "src",
            "count": "401,356"
        },
        {
            "word": "ref",
            "count": "400,030"
        },
        {
            "word": "TestCase",
            "count": "399,937"
        },
        {
            "word": "process",
            "count": "399,472"
        },
        {
            "word": "startswith",
            "count": "399,064"
        },
        {
            "word": "Get",
            "count": "398,663"
        },
        {
            "word": "Column",
            "count": "398,126"
        },
        {
            "word": "empty",
            "count": "397,984"
        },
        {
            "word": "POST",
            "count": "396,823"
        },
        {
            "word": "see",
            "count": "396,627"
        },
        {
            "word": "some",
            "count": "395,249"
        },
        {
            "word": "properties",
            "count": "394,692"
        },
        {
            "word": "add_constructor",
            "count": "394,625"
        },
        {
            "word": "users",
            "count": "394,471"
        },
        {
            "word": "B",
            "count": "394,153"
        },
        {
            "word": "fake",
            "count": "394,153"
        },
        {
            "word": "block",
            "count": "393,666"
        },
        {
            "word": "axis",
            "count": "392,833"
        },
        {
            "word": "No",
            "count": "391,928"
        },
        {
            "word": "database",
            "count": "391,661"
        },
        {
            "word": "rtype",
            "count": "391,547"
        },
        {
            "word": "lower",
            "count": "391,517"
        },
        {
            "word": "false",
            "count": "391,293"
        },
        {
            "word": "op",
            "count": "391,006"
        },
        {
            "word": "information",
            "count": "389,070"
        },
        {
            "word": "ext",
            "count": "387,902"
        },
        {
            "word": "widget",
            "count": "387,448"
        },
        {
            "word": "mox",
            "count": "386,056"
        },
        {
            "word": "lib",
            "count": "384,295"
        },
        {
            "word": "ImportError",
            "count": "383,954"
        },
        {
            "word": "opts",
            "count": "383,505"
        },
        {
            "word": "store",
            "count": "383,472"
        },
        {
            "word": "tags",
            "count": "383,323"
        },
        {
            "word": "related",
            "count": "383,158"
        },
        {
            "word": "is_virtual",
            "count": "382,360"
        },
        {
            "word": "need",
            "count": "381,183"
        },
        {
            "word": "CONF",
            "count": "381,119"
        },
        {
            "word": "Check",
            "count": "379,432"
        },
        {
            "word": "unicode",
            "count": "378,718"
        },
        {
            "word": "cms",
            "count": "378,700"
        },
        {
            "word": "available",
            "count": "378,084"
        },
        {
            "word": "ForeignKey",
            "count": "376,675"
        },
        {
            "word": "make",
            "count": "375,398"
        },
        {
            "word": "attrs",
            "count": "374,317"
        },
        {
            "word": "L",
            "count": "374,310"
        },
        {
            "word": "Type",
            "count": "373,913"
        },
        {
            "word": "QtGui",
            "count": "373,643"
        },
        {
            "word": "there",
            "count": "373,273"
        },
        {
            "word": "types",
            "count": "373,018"
        },
        {
            "word": "variable",
            "count": "372,447"
        },
        {
            "word": "access",
            "count": "372,304"
        },
        {
            "word": "author",
            "count": "370,572"
        },
        {
            "word": "before",
            "count": "370,082"
        },
        {
            "word": "dev",
            "count": "368,060"
        },
        {
            "word": "dest",
            "count": "366,068"
        },
        {
            "word": "argument",
            "count": "363,641"
        },
        {
            "word": "tree",
            "count": "363,375"
        },
        {
            "word": "limit",
            "count": "362,828"
        },
        {
            "word": "its",
            "count": "360,580"
        },
        {
            "word": "dictionary",
            "count": "358,398"
        },
        {
            "word": "build",
            "count": "357,835"
        },
        {
            "word": "__class__",
            "count": "356,648"
        },
        {
            "word": "interface",
            "count": "355,715"
        },
        {
            "word": "global",
            "count": "355,591"
        },
        {
            "word": "long",
            "count": "355,480"
        },
        {
            "word": "stop",
            "count": "355,457"
        },
        {
            "word": "We",
            "count": "354,851"
        },
        {
            "word": "GET",
            "count": "354,840"
        },
        {
            "word": "platform",
            "count": "354,805"
        },
        {
            "word": "util",
            "count": "354,606"
        },
        {
            "word": "Y",
            "count": "354,070"
        },
        {
            "word": "include",
            "count": "353,413"
        },
        {
            "word": "List",
            "count": "352,725"
        },
        {
            "word": "load",
            "count": "352,596"
        },
        {
            "word": "connect",
            "count": "349,781"
        },
        {
            "word": "pk",
            "count": "348,988"
        },
        {
            "word": "language",
            "count": "348,941"
        },
        {
            "word": "Error",
            "count": "348,611"
        },
        {
            "word": "valid",
            "count": "347,766"
        },
        {
            "word": "commit",
            "count": "347,491"
        },
        {
            "word": "double",
            "count": "347,214"
        },
        {
            "word": "www",
            "count": "346,476"
        },
        {
            "word": "API",
            "count": "345,946"
        },
        {
            "word": "also",
            "count": "345,007"
        },
        {
            "word": "success",
            "count": "343,803"
        },
        {
            "word": "handler",
            "count": "343,776"
        },
        {
            "word": "AttributeError",
            "count": "343,725"
        },
        {
            "word": "BooleanField",
            "count": "343,641"
        },
        {
            "word": "right",
            "count": "342,500"
        },
        {
            "word": "NotImplementedError",
            "count": "341,643"
        },
        {
            "word": "than",
            "count": "340,996"
        },
        {
            "word": "non",
            "count": "339,763"
        },
        {
            "word": "login",
            "count": "339,402"
        },
        {
            "word": "constructor",
            "count": "339,299"
        },
        {
            "word": "script",
            "count": "339,032"
        },
        {
            "word": "your",
            "count": "337,737"
        },
        {
            "word": "kw",
            "count": "337,340"
        },
        {
            "word": "__str__",
            "count": "336,617"
        },
        {
            "word": "left",
            "count": "336,548"
        },
        {
            "word": "unique",
            "count": "336,364"
        },
        {
            "word": "paths",
            "count": "335,390"
        },
        {
            "word": "requests",
            "count": "334,337"
        },
        {
            "word": "site",
            "count": "332,524"
        },
        {
            "word": "math",
            "count": "332,303"
        },
        {
            "word": "views",
            "count": "332,069"
        },
        {
            "word": "M",
            "count": "331,811"
        },
        {
            "word": "position",
            "count": "330,514"
        },
        {
            "word": "tf",
            "count": "329,166"
        },
        {
            "word": "filters",
            "count": "328,871"
        },
        {
            "word": "don",
            "count": "328,310"
        },
        {
            "word": "comment",
            "count": "328,057"
        },
        {
            "word": "height",
            "count": "327,717"
        },
        {
            "word": "color",
            "count": "327,530"
        },
        {
            "word": "handle",
            "count": "327,089"
        },
        {
            "word": "returned",
            "count": "326,921"
        },
        {
            "word": "six",
            "count": "326,243"
        },
        {
            "word": "ctxt",
            "count": "325,814"
        },
        {
            "word": "assertFalse",
            "count": "325,478"
        },
        {
            "word": "last",
            "count": "325,206"
        },
        {
            "word": "relative",
            "count": "324,404"
        },
        {
            "word": "already",
            "count": "324,223"
        },
        {
            "word": "rows",
            "count": "323,455"
        },
        {
            "word": "failed",
            "count": "323,386"
        },
        {
            "word": "category",
            "count": "322,866"
        },
        {
            "word": "project_id",
            "count": "321,641"
        },
        {
            "word": "been",
            "count": "319,742"
        },
        {
            "word": "dir",
            "count": "319,343"
        },
        {
            "word": "var",
            "count": "318,378"
        },
        {
            "word": "Name",
            "count": "317,786"
        },
        {
            "word": "DEBUG",
            "count": "316,684"
        },
        {
            "word": "N",
            "count": "316,295"
        },
        {
            "word": "parse",
            "count": "313,999"
        },
        {
            "word": "__repr__",
            "count": "313,883"
        },
        {
            "word": "section",
            "count": "313,864"
        },
        {
            "word": "modules",
            "count": "313,259"
        },
        {
            "word": "HTML",
            "count": "312,225"
        },
        {
            "word": "support",
            "count": "311,753"
        },
        {
            "word": "two",
            "count": "311,397"
        },
        {
            "word": "td",
            "count": "309,563"
        },
        {
            "word": "eq_",
            "count": "309,278"
        },
        {
            "word": "map",
            "count": "308,469"
        },
        {
            "word": "plugin",
            "count": "307,632"
        },
        {
            "word": "Model",
            "count": "307,371"
        },
        {
            "word": "max",
            "count": "305,991"
        },
        {
            "word": "documentation",
            "count": "305,157"
        },
        {
            "word": "loads",
            "count": "304,494"
        },
        {
            "word": "tr",
            "count": "303,387"
        },
        {
            "word": "extra",
            "count": "302,935"
        },
        {
            "word": "parameter",
            "count": "302,808"
        },
        {
            "word": "expr",
            "count": "302,687"
        },
        {
            "word": "unit",
            "count": "301,413"
        },
        {
            "word": "iprot",
            "count": "301,292"
        },
        {
            "word": "send",
            "count": "301,230"
        },
        {
            "word": "buffer",
            "count": "301,067"
        },
        {
            "word": "integer",
            "count": "300,899"
        },
        {
            "word": "container",
            "count": "300,851"
        },
        {
            "word": "methods",
            "count": "299,290"
        },
        {
            "word": "groups",
            "count": "298,865"
        },
        {
            "word": "children",
            "count": "297,984"
        },
        {
            "word": "outfile",
            "count": "296,846"
        },
        {
            "word": "Content",
            "count": "296,412"
        },
        {
            "word": "docs",
            "count": "296,128"
        },
        {
            "word": "wx",
            "count": "296,123"
        },
        {
            "word": "defaults",
            "count": "295,232"
        },
        {
            "word": "oprot",
            "count": "294,446"
        },
        {
            "word": "instances",
            "count": "294,215"
        },
        {
            "word": "stats",
            "count": "293,149"
        },
        {
            "word": "insert",
            "count": "292,945"
        },
        {
            "word": "render",
            "count": "292,900"
        },
        {
            "word": "TODO",
            "count": "292,660"
        },
        {
            "word": "stack",
            "count": "291,154"
        },
        {
            "word": "usage",
            "count": "289,910"
        },
        {
            "word": "release",
            "count": "289,802"
        },
        {
            "word": "controller",
            "count": "289,772"
        },
        {
            "word": "buf",
            "count": "289,550"
        },
        {
            "word": "getLogger",
            "count": "289,534"
        },
        {
            "word": "warnings",
            "count": "289,274"
        },
        {
            "word": "register",
            "count": "289,149"
        },
        {
            "word": "It",
            "count": "288,914"
        },
        {
            "word": "ip",
            "count": "288,870"
        },
        {
            "word": "added",
            "count": "288,569"
        },
        {
            "word": "sequence",
            "count": "288,296"
        },
        {
            "word": "raw",
            "count": "286,463"
        },
        {
            "word": "local",
            "count": "285,243"
        },
        {
            "word": "manager",
            "count": "284,645"
        },
        {
            "word": "pytest",
            "count": "284,220"
        },
        {
            "word": "product",
            "count": "284,051"
        },
        {
            "word": "top",
            "count": "283,682"
        },
        {
            "word": "bytes",
            "count": "282,872"
        },
        {
            "word": "window",
            "count": "282,686"
        },
        {
            "word": "rule",
            "count": "282,574"
        },
        {
            "word": "following",
            "count": "281,325"
        },
        {
            "word": "done",
            "count": "280,597"
        },
        {
            "word": "channel",
            "count": "280,037"
        },
        {
            "word": "sort",
            "count": "278,574"
        },
        {
            "word": "sure",
            "count": "278,448"
        },
        {
            "word": "IntegerField",
            "count": "278,234"
        },
        {
            "word": "extend",
            "count": "278,098"
        },
        {
            "word": "struct",
            "count": "278,098"
        },
        {
            "word": "String",
            "count": "278,095"
        },
        {
            "word": "fail",
            "count": "278,023"
        },
        {
            "word": "dumps",
            "count": "277,992"
        },
        {
            "word": "char",
            "count": "277,819"
        },
        {
            "word": "P",
            "count": "277,389"
        },
        {
            "word": "encode",
            "count": "277,074"
        },
        {
            "word": "Note",
            "count": "276,973"
        },
        {
            "word": "just",
            "count": "276,709"
        },
        {
            "word": "constants",
            "count": "276,281"
        },
        {
            "word": "package",
            "count": "276,156"
        },
        {
            "word": "compile",
            "count": "276,115"
        },
        {
            "word": "meta",
            "count": "275,813"
        },
        {
            "word": "extensions",
            "count": "275,715"
        },
        {
            "word": "net",
            "count": "275,626"
        },
        {
            "word": "testing",
            "count": "275,608"
        },
        {
            "word": "idx",
            "count": "275,528"
        },
        {
            "word": "change",
            "count": "275,458"
        },
        {
            "word": "content_type",
            "count": "275,371"
        },
        {
            "word": "signal",
            "count": "275,016"
        },
        {
            "word": "deleted",
            "count": "274,791"
        },
        {
            "word": "std",
            "count": "274,757"
        },
        {
            "word": "namespace",
            "count": "274,332"
        },
        {
            "word": "timestamp",
            "count": "273,806"
        },
        {
            "word": "StringIO",
            "count": "273,214"
        },
        {
            "word": "traceback",
            "count": "271,924"
        },
        {
            "word": "exp",
            "count": "271,341"
        },
        {
            "word": "without",
            "count": "270,934"
        },
        {
            "word": "move",
            "count": "270,896"
        },
        {
            "word": "step",
            "count": "270,386"
        },
        {
            "word": "unicode_literals",
            "count": "270,143"
        },
        {
            "word": "columns",
            "count": "269,959"
        },
        {
            "word": "Request",
            "count": "269,953"
        },
        {
            "word": "fp",
            "count": "269,827"
        },
        {
            "word": "urls",
            "count": "269,416"
        },
        {
            "word": "display",
            "count": "268,639"
        },
        {
            "word": "middleware",
            "count": "268,224"
        },
        {
            "word": "protocol",
            "count": "267,883"
        },
        {
            "word": "generated",
            "count": "266,937"
        },
        {
            "word": "active",
            "count": "266,844"
        },
        {
            "word": "pages",
            "count": "266,781"
        },
        {
            "word": "provided",
            "count": "265,676"
        },
        {
            "word": "warning",
            "count": "265,495"
        },
        {
            "word": "Ptr",
            "count": "264,892"
        },
        {
            "word": "txt",
            "count": "261,562"
        },
        {
            "word": "parts",
            "count": "260,460"
        },
        {
            "word": "invalid",
            "count": "259,339"
        },
        {
            "word": "updated",
            "count": "259,319"
        },
        {
            "word": "commands",
            "count": "259,219"
        },
        {
            "word": "because",
            "count": "259,088"
        },
        {
            "word": "details",
            "count": "258,557"
        },
        {
            "word": "running",
            "count": "258,283"
        },
        {
            "word": "disable",
            "count": "257,204"
        },
        {
            "word": "urllib",
            "count": "256,934"
        },
        {
            "word": "point",
            "count": "256,627"
        },
        {
            "word": "images",
            "count": "256,179"
        },
        {
            "word": "single",
            "count": "255,381"
        },
        {
            "word": "tools",
            "count": "254,964"
        },
        {
            "word": "reason",
            "count": "254,853"
        },
        {
            "word": "strings",
            "count": "254,806"
        },
        {
            "word": "D",
            "count": "254,769"
        },
        {
            "word": "contents",
            "count": "254,333"
        },
        {
            "word": "binary",
            "count": "254,175"
        },
        {
            "word": "choices",
            "count": "253,803"
        },
        {
            "word": "TextField",
            "count": "253,384"
        },
        {
            "word": "sub",
            "count": "253,083"
        },
        {
            "word": "flush",
            "count": "252,533"
        },
        {
            "word": "passed",
            "count": "251,734"
        },
        {
            "word": "loop",
            "count": "251,663"
        },
        {
            "word": "functions",
            "count": "251,301"
        },
        {
            "word": "links",
            "count": "250,797"
        },
        {
            "word": "collections",
            "count": "250,775"
        },
        {
            "word": "changed",
            "count": "250,616"
        },
        {
            "word": "they",
            "count": "250,284"
        },
        {
            "word": "schema",
            "count": "249,017"
        },
        {
            "word": "events",
            "count": "248,266"
        },
        {
            "word": "js",
            "count": "248,071"
        },
        {
            "word": "frame",
            "count": "247,804"
        },
        {
            "word": "desc",
            "count": "247,775"
        },
        {
            "word": "engine",
            "count": "247,668"
        },
        {
            "word": "classes",
            "count": "246,486"
        },
        {
            "word": "doesn",
            "count": "246,028"
        },
        {
            "word": "dt",
            "count": "245,993"
        },
        {
            "word": "total",
            "count": "245,614"
        },
        {
            "word": "abspath",
            "count": "245,031"
        },
        {
            "word": "fd",
            "count": "244,908"
        },
        {
            "word": "clear",
            "count": "244,854"
        },
        {
            "word": "abc",
            "count": "244,614"
        },
        {
            "word": "actions",
            "count": "243,067"
        },
        {
            "word": "fname",
            "count": "243,021"
        },
        {
            "word": "Mock",
            "count": "242,599"
        },
        {
            "word": "sql",
            "count": "242,433"
        },
        {
            "word": "want",
            "count": "242,392"
        },
        {
            "word": "tmp",
            "count": "241,790"
        },
        {
            "word": "font",
            "count": "241,614"
        },
        {
            "word": "raises",
            "count": "241,575"
        },
        {
            "word": "Language",
            "count": "241,445"
        },
        {
            "word": "__file__",
            "count": "240,698"
        },
        {
            "word": "num",
            "count": "240,408"
        },
        {
            "word": "specific",
            "count": "240,108"
        },
        {
            "word": "storage",
            "count": "239,858"
        },
        {
            "word": "about",
            "count": "239,820"
        },
        {
            "word": "disk",
            "count": "239,390"
        },
        {
            "word": "flag",
            "count": "239,046"
        },
        {
            "word": "profile",
            "count": "238,395"
        },
        {
            "word": "pattern",
            "count": "237,958"
        },
        {
            "word": "sympy",
            "count": "237,627"
        },
        {
            "word": "wait",
            "count": "237,615"
        },
        {
            "word": "defined",
            "count": "237,092"
        },
        {
            "word": "fn",
            "count": "236,858"
        },
        {
            "word": "xrange",
            "count": "236,331"
        },
        {
            "word": "de",
            "count": "236,108"
        },
        {
            "word": "variables",
            "count": "236,053"
        },
        {
            "word": "enabled",
            "count": "236,036"
        },
        {
            "word": "skip",
            "count": "235,634"
        },
        {
            "word": "mask",
            "count": "235,485"
        },
        {
            "word": "shutil",
            "count": "235,380"
        },
        {
            "word": "role",
            "count": "235,352"
        },
        {
            "word": "job",
            "count": "235,292"
        },
        {
            "word": "them",
            "count": "235,161"
        },
        {
            "word": "min",
            "count": "234,477"
        },
        {
            "word": "contain",
            "count": "234,461"
        },
        {
            "word": "assertIn",
            "count": "234,246"
        },
        {
            "word": "H",
            "count": "234,241"
        },
        {
            "word": "div",
            "count": "233,347"
        },
        {
            "word": "In",
            "count": "232,835"
        },
        {
            "word": "queue",
            "count": "232,788"
        },
        {
            "word": "thread",
            "count": "232,263"
        },
        {
            "word": "OK",
            "count": "232,054"
        },
        {
            "word": "instead",
            "count": "231,278"
        },
        {
            "word": "__dict__",
            "count": "230,852"
        },
        {
            "word": "these",
            "count": "230,367"
        },
        {
            "word": "slug",
            "count": "230,271"
        },
        {
            "word": "such",
            "count": "229,842"
        },
        {
            "word": "decode",
            "count": "229,683"
        },
        {
            "word": "extension",
            "count": "228,541"
        },
        {
            "word": "operator",
            "count": "228,107"
        },
        {
            "word": "col",
            "count": "227,644"
        },
        {
            "word": "Time",
            "count": "227,252"
        },
        {
            "word": "operation",
            "count": "227,148"
        },
        {
            "word": "work",
            "count": "226,629"
        },
        {
            "word": "redirect",
            "count": "226,571"
        },
        {
            "word": "inputs",
            "count": "226,191"
        },
        {
            "word": "labels",
            "count": "225,947"
        },
        {
            "word": "containing",
            "count": "225,770"
        },
        {
            "word": "payload",
            "count": "225,224"
        },
        {
            "word": "ex",
            "count": "225,154"
        },
        {
            "word": "IOError",
            "count": "225,072"
        },
        {
            "word": "Default",
            "count": "224,858"
        },
        {
            "word": "Migration",
            "count": "224,377"
        },
        {
            "word": "sum",
            "count": "224,334"
        },
        {
            "word": "full",
            "count": "223,085"
        },
        {
            "word": "vals",
            "count": "223,027"
        },
        {
            "word": "custom",
            "count": "222,710"
        },
        {
            "word": "reference",
            "count": "222,330"
        },
        {
            "word": "enumerate",
            "count": "221,862"
        },
        {
            "word": "subject",
            "count": "221,435"
        },
        {
            "word": "Item",
            "count": "220,281"
        },
        {
            "word": "An",
            "count": "219,970"
        },
        {
            "word": "pid",
            "count": "219,847"
        },
        {
            "word": "factory",
            "count": "219,615"
        },
        {
            "word": "sorted",
            "count": "219,395"
        },
        {
            "word": "matrix",
            "count": "218,948"
        },
        {
            "word": "course_id",
            "count": "217,820"
        },
        {
            "word": "router",
            "count": "217,781"
        },
        {
            "word": "iteritems",
            "count": "217,542"
        },
        {
            "word": "put",
            "count": "217,340"
        },
        {
            "word": "templates",
            "count": "216,587"
        },
        {
            "word": "HTTP",
            "count": "216,424"
        },
        {
            "word": "kind",
            "count": "215,947"
        },
        {
            "word": "stubs",
            "count": "215,869"
        },
        {
            "word": "neutron",
            "count": "215,825"
        },
        {
            "word": "threading",
            "count": "215,773"
        },
        {
            "word": "subnet",
            "count": "215,633"
        },
        {
            "word": "matplotlib",
            "count": "215,405"
        },
        {
            "word": "agent",
            "count": "214,758"
        },
        {
            "word": "resources",
            "count": "214,672"
        },
        {
            "word": "spec",
            "count": "213,465"
        },
        {
            "word": "x20",
            "count": "213,423"
        },
        {
            "word": "validate",
            "count": "213,033"
        },
        {
            "word": "Integer",
            "count": "212,617"
        },
        {
            "word": "Node",
            "count": "211,871"
        },
        {
            "word": "TypeId",
            "count": "210,975"
        },
        {
            "word": "exist",
            "count": "210,163"
        },
        {
            "word": "multiple",
            "count": "209,931"
        },
        {
            "word": "Examples",
            "count": "209,493"
        },
        {
            "word": "uint8_t",
            "count": "208,359"
        },
        {
            "word": "seconds",
            "count": "208,119"
        },
        {
            "word": "print_function",
            "count": "207,993"
        },
        {
            "word": "rc",
            "count": "207,927"
        },
        {
            "word": "pi",
            "count": "207,189"
        },
        {
            "word": "ns",
            "count": "206,761"
        },
        {
            "word": "add_argument",
            "count": "206,254"
        },
        {
            "word": "alpha",
            "count": "206,241"
        },
        {
            "word": "changes",
            "count": "205,936"
        },
        {
            "word": "based",
            "count": "205,817"
        },
        {
            "word": "layer",
            "count": "205,659"
        },
        {
            "word": "absolute_import",
            "count": "205,054"
        },
        {
            "word": "FROM",
            "count": "204,912"
        },
        {
            "word": "etc",
            "count": "204,340"
        },
        {
            "word": "points",
            "count": "204,194"
        },
        {
            "word": "boolean",
            "count": "204,033"
        },
        {
            "word": "menu",
            "count": "204,002"
        },
        {
            "word": "ax",
            "count": "203,938"
        },
        {
            "word": "sqrt",
            "count": "203,808"
        },
        {
            "word": "scope",
            "count": "203,574"
        },
        {
            "word": "operations",
            "count": "203,116"
        },
        {
            "word": "css",
            "count": "203,023"
        },
        {
            "word": "since",
            "count": "202,930"
        },
        {
            "word": "argparse",
            "count": "202,814"
        },
        {
            "word": "between",
            "count": "202,643"
        },
        {
            "word": "ignore",
            "count": "202,112"
        },
        {
            "word": "being",
            "count": "202,067"
        },
        {
            "word": "uri",
            "count": "201,219"
        },
        {
            "word": "contains",
            "count": "200,937"
        },
        {
            "word": "actual",
            "count": "200,422"
        },
        {
            "word": "word",
            "count": "200,294"
        },
        {
            "word": "entries",
            "count": "200,138"
        },
        {
            "word": "backend",
            "count": "199,634"
        },
        {
            "word": "ftype",
            "count": "199,389"
        },
        {
            "word": "either",
            "count": "199,226"
        },
        {
            "word": "year",
            "count": "198,852"
        },
        {
            "word": "F",
            "count": "198,822"
        },
        {
            "word": "ln",
            "count": "198,647"
        },
        {
            "word": "browse",
            "count": "197,837"
        },
        {
            "word": "plugins",
            "count": "197,824"
        },
        {
            "word": "lang",
            "count": "197,674"
        },
        {
            "word": "expression",
            "count": "197,633"
        },
        {
            "word": "sqlalchemy",
            "count": "197,450"
        },
        {
            "word": "correct",
            "count": "197,178"
        },
        {
            "word": "environment",
            "count": "197,168"
        },
        {
            "word": "library",
            "count": "196,916"
        },
        {
            "word": "pack",
            "count": "196,828"
        },
        {
            "word": "OSError",
            "count": "196,673"
        },
        {
            "word": "supported",
            "count": "196,046"
        },
        {
            "word": "pylint",
            "count": "195,603"
        },
        {
            "word": "AndReturn",
            "count": "195,570"
        },
        {
            "word": "Example",
            "count": "195,255"
        },
        {
            "word": "rules",
            "count": "195,064"
        },
        {
            "word": "what",
            "count": "194,686"
        },
        {
            "word": "hash",
            "count": "194,608"
        },
        {
            "word": "gtk",
            "count": "194,155"
        },
        {
            "word": "suffix",
            "count": "194,079"
        },
        {
            "word": "old",
            "count": "193,486"
        },
        {
            "word": "matches",
            "count": "193,483"
        },
        {
            "word": "distribution",
            "count": "193,148"
        },
        {
            "word": "href",
            "count": "193,103"
        },
        {
            "word": "keyword",
            "count": "192,797"
        },
        {
            "word": "tenant_id",
            "count": "192,661"
        },
        {
            "word": "button",
            "count": "192,489"
        },
        {
            "word": "sa",
            "count": "192,389"
        },
        {
            "word": "tempfile",
            "count": "192,350"
        },
        {
            "word": "Q",
            "count": "192,286"
        },
        {
            "word": "real",
            "count": "192,219"
        },
        {
            "word": "warn",
            "count": "192,102"
        },
        {
            "word": "policy",
            "count": "192,054"
        },
        {
            "word": "snapshot",
            "count": "191,888"
        },
        {
            "word": "Make",
            "count": "191,796"
        },
        {
            "word": "packet",
            "count": "191,699"
        },
        {
            "word": "st",
            "count": "191,609"
        },
        {
            "word": "v2",
            "count": "191,558"
        },
        {
            "word": "G",
            "count": "191,414"
        },
        {
            "word": "translation",
            "count": "190,912"
        },
        {
            "word": "dependencies",
            "count": "190,825"
        },
        {
            "word": "You",
            "count": "190,788"
        },
        {
            "word": "arg0",
            "count": "190,735"
        },
        {
            "word": "Invalid",
            "count": "190,509"
        },
        {
            "word": "opt",
            "count": "190,268"
        },
        {
            "word": "elements",
            "count": "190,247"
        },
        {
            "word": "whether",
            "count": "190,195"
        },
        {
            "word": "clean",
            "count": "189,345"
        },
        {
            "word": "second",
            "count": "189,178"
        },
        {
            "word": "diff",
            "count": "188,449"
        },
        {
            "word": "present",
            "count": "188,088"
        },
        {
            "word": "master",
            "count": "187,812"
        },
        {
            "word": "servers",
            "count": "187,782"
        },
        {
            "word": "google",
            "count": "187,662"
        },
        {
            "word": "cluster",
            "count": "187,649"
        },
        {
            "word": "io",
            "count": "187,495"
        },
        {
            "word": "reset",
            "count": "187,024"
        },
        {
            "word": "graph",
            "count": "186,651"
        },
        {
            "word": "layout",
            "count": "186,209"
        },
        {
            "word": "QtCore",
            "count": "185,683"
        },
        {
            "word": "tokens",
            "count": "185,333"
        },
        {
            "word": "different",
            "count": "185,320"
        },
        {
            "word": "tearDown",
            "count": "185,179"
        },
        {
            "word": "cannot",
            "count": "185,136"
        },
        {
            "word": "inst",
            "count": "185,001"
        },
        {
            "word": "missing",
            "count": "184,780"
        },
        {
            "word": "back",
            "count": "184,644"
        },
        {
            "word": "parse_args",
            "count": "184,440"
        },
        {
            "word": "urllib2",
            "count": "184,039"
        },
        {
            "word": "hostname",
            "count": "183,968"
        },
        {
            "word": "sock",
            "count": "183,767"
        },
        {
            "word": "Options",
            "count": "183,384"
        },
        {
            "word": "devices",
            "count": "183,354"
        },
        {
            "word": "Use",
            "count": "183,241"
        },
        {
            "word": "addr",
            "count": "183,086"
        },
        {
            "word": "locale",
            "count": "183,039"
        },
        {
            "word": "selected",
            "count": "183,004"
        }
    ]
}